[
  {
    "id": 1,
    "pais": "Brasil",
    "ano": "2006",
    "serie": "A",
    "rodada": "1",
    "data": "2006-04-15",
    "horario": "18h10",
    "time1": "44",
    "time2": "54",
    "placar1": "1",
    "placar2": "0"
  },
  {
    "id": 2,
    "pais": "Brasil",
    "ano": 2006,
    "serie": "A",
    "rodada": "1",
    "data": "2006-04-15",
    "horario": "18h10",
    "time1": "71",
    "time2": "40",
    "placar1": "1",
    "placar2": "1"
  },
  {
    "id": 3,
    "pais": "Brasil",
    "ano": 2006,
    "serie": "A",
    "rodada": "1",
    "data": "2006-04-16",
    "horario": "16h00",
    "time1": "66",
    "time2": "25",
    "placar1": "2",
    "placar2": "1"
  },
  {
    "id": 4,
    "pais": "Brasil",
    "ano": 2006,
    "serie": "A",
    "rodada": "1",
    "data": "2006-04-16",
    "horario": "16h00",
    "time1": "67",
    "time2": "30",
    "placar1": "1",
    "placar2": "0"
  },
  {
    "id": 5,
    "pais": "Brasil",
    "ano": 2006,
    "serie": "A",
    "rodada": "1",
    "data": "2006-04-16",
    "horario": "16h00",
    "time1": "36",
    "time2": "21",
    "placar1": "2",
    "placar2": "0"
  },
  {
    "id": 6,
    "pais": "Brasil",
    "ano": 2006,
    "serie": "A",
    "rodada": "1",
    "data": "2006-04-16",
    "horario": "16h00",
    "time1": "11",
    "time2": "32",
    "placar1": "1",
    "placar2": "0"
  },
  {
    "id": 7,
    "pais": "Brasil",
    "ano": 2006,
    "serie": "A",
    "rodada": "1",
    "data": "2006-04-16",
    "horario": "18h10",
    "time1": "34",
    "time2": "64",
    "placar1": "0",
    "placar2": "0"
  },
  {
    "id": 8,
    "pais": "Brasil",
    "ano": 2006,
    "serie": "A",
    "rodada": "1",
    "data": "2006-04-16",
    "horario": "18h10",
    "time1": "5",
    "time2": "31",
    "placar1": "1",
    "placar2": "2"
  },
  {
    "id": 9,
    "pais": "Brasil",
    "ano": 2006,
    "serie": "A",
    "rodada": "1",
    "data": "2006-04-16",
    "horario": "18h10",
    "time1": "62",
    "time2": "29",
    "placar1": "0",
    "placar2": "0"
  },
  {
    "id": 10,
    "pais": "Brasil",
    "ano": 2006,
    "serie": "A",
    "rodada": "1",
    "data": "2006-04-16",
    "horario": "18h10",
    "time1": "53",
    "time2": "57",
    "placar1": "2",
    "placar2": "3"
  },
  {
    "id": 11,
    "pais": "Brasil",
    "ano": 2006,
    "serie": "A",
    "rodada": "2",
    "data": "2006-04-22",
    "horario": "16h00",
    "time1": "21",
    "time2": "66",
    "placar1": "3",
    "placar2": "0"
  },
  {
    "id": 12,
    "pais": "Brasil",
    "ano": 2006,
    "serie": "A",
    "rodada": "2",
    "data": "2006-04-22",
    "horario": "18h10",
    "time1": "31",
    "time2": "34",
    "placar1": "1",
    "placar2": "0"
  },
  {
    "id": 13,
    "pais": "Brasil",
    "ano": 2006,
    "serie": "A",
    "rodada": "2",
    "data": "2006-04-22",
    "horario": "18h10",
    "time1": "29",
    "time2": "53",
    "placar1": "6",
    "placar2": "1"
  },
  {
    "id": 14,
    "pais": "Brasil",
    "ano": 2006,
    "serie": "A",
    "rodada": "2",
    "data": "2006-04-23",
    "horario": "16h00",
    "time1": "64",
    "time2": "5",
    "placar1": "2",
    "placar2": "0"
  },
  {
    "id": 15,
    "pais": "Brasil",
    "ano": 2006,
    "serie": "A",
    "rodada": "2",
    "data": "2006-04-23",
    "horario": "16h00",
    "time1": "40",
    "time2": "62",
    "placar1": "1",
    "placar2": "0"
  },
  {
    "id": 16,
    "pais": "Brasil",
    "ano": 2006,
    "serie": "A",
    "rodada": "2",
    "data": "2006-04-23",
    "horario": "16h00",
    "time1": "57",
    "time2": "71",
    "placar1": "1",
    "placar2": "2"
  },
  {
    "id": 17,
    "pais": "Brasil",
    "ano": 2006,
    "serie": "A",
    "rodada": "2",
    "data": "2006-04-23",
    "horario": "16h00",
    "time1": "30",
    "time2": "44",
    "placar1": "3",
    "placar2": "1"
  },
  {
    "id": 18,
    "pais": "Brasil",
    "ano": 2006,
    "serie": "A",
    "rodada": "2",
    "data": "2006-04-23",
    "horario": "18h10",
    "time1": "54",
    "time2": "11",
    "placar1": "0",
    "placar2": "0"
  },
  {
    "id": 19,
    "pais": "Brasil",
    "ano": 2006,
    "serie": "A",
    "rodada": "2",
    "data": "2006-04-23",
    "horario": "18h10",
    "time1": "32",
    "time2": "67",
    "placar1": "1",
    "placar2": "0"
  },
  {
    "id": 20,
    "pais": "Brasil",
    "ano": 2006,
    "serie": "A",
    "rodada": "2",
    "data": "2006-04-23",
    "horario": "18h10",
    "time1": "25",
    "time2": "36",
    "placar1": "3",
    "placar2": "1"
  },
  {
    "id": 21,
    "pais": "Brasil",
    "ano": 2006,
    "serie": "A",
    "rodada": "3",
    "data": "2006-04-29",
    "horario": "16h00",
    "time1": "32",
    "time2": "66",
    "placar1": "2",
    "placar2": "1"
  },
  {
    "id": 22,
    "pais": "Brasil",
    "ano": 2006,
    "serie": "A",
    "rodada": "3",
    "data": "2006-04-29",
    "horario": "18h10",
    "time1": "67",
    "time2": "62",
    "placar1": "4",
    "placar2": "0"
  },
  {
    "id": 23,
    "pais": "Brasil",
    "ano": 2006,
    "serie": "A",
    "rodada": "3",
    "data": "2006-04-29",
    "horario": "18h10",
    "time1": "11",
    "time2": "5",
    "placar1": "0",
    "placar2": "4"
  },
  {
    "id": 24,
    "pais": "Brasil",
    "ano": 2006,
    "serie": "A",
    "rodada": "3",
    "data": "2006-04-30",
    "horario": "16h00",
    "time1": "57",
    "time2": "21",
    "placar1": "3",
    "placar2": "2"
  },
  {
    "id": 25,
    "pais": "Brasil",
    "ano": 2006,
    "serie": "A",
    "rodada": "3",
    "data": "2006-04-30",
    "horario": "16h00",
    "time1": "54",
    "time2": "36",
    "placar1": "5",
    "placar2": "2"
  },
  {
    "id": 26,
    "pais": "Brasil",
    "ano": 2006,
    "serie": "A",
    "rodada": "3",
    "data": "2006-04-30",
    "horario": "16h00",
    "time1": "53",
    "time2": "64",
    "placar1": "1",
    "placar2": "2"
  },
  {
    "id": 27,
    "pais": "Brasil",
    "ano": 2006,
    "serie": "A",
    "rodada": "3",
    "data": "2006-04-30",
    "horario": "16h00",
    "time1": "40",
    "time2": "30",
    "placar1": "1",
    "placar2": "0"
  },
  {
    "id": 28,
    "pais": "Brasil",
    "ano": 2006,
    "serie": "A",
    "rodada": "3",
    "data": "2006-04-30",
    "horario": "18h10",
    "time1": "71",
    "time2": "31",
    "placar1": "1",
    "placar2": "1"
  },
  {
    "id": 29,
    "pais": "Brasil",
    "ano": 2006,
    "serie": "A",
    "rodada": "3",
    "data": "2006-04-30",
    "horario": "18h10",
    "time1": "44",
    "time2": "34",
    "placar1": "1",
    "placar2": "1"
  },
  {
    "id": 30,
    "pais": "Brasil",
    "ano": 2006,
    "serie": "A",
    "rodada": "3",
    "data": "2006-04-30",
    "horario": "18h10",
    "time1": "29",
    "time2": "25",
    "placar1": "0",
    "placar2": "2"
  },
  {
    "id": 31,
    "pais": "Brasil",
    "ano": 2006,
    "serie": "A",
    "rodada": "4",
    "data": "2006-05-06",
    "horario": "16h00",
    "time1": "62",
    "time2": "57",
    "placar1": "1",
    "placar2": "1"
  },
  {
    "id": 32,
    "pais": "Brasil",
    "ano": 2006,
    "serie": "A",
    "rodada": "4",
    "data": "2006-05-06",
    "horario": "18h10",
    "time1": "64",
    "time2": "32",
    "placar1": "2",
    "placar2": "0"
  },
  {
    "id": 33,
    "pais": "Brasil",
    "ano": 2006,
    "serie": "A",
    "rodada": "4",
    "data": "2006-05-06",
    "horario": "18h10",
    "time1": "31",
    "time2": "54",
    "placar1": "2",
    "placar2": "1"
  },
  {
    "id": 34,
    "pais": "Brasil",
    "ano": 2006,
    "serie": "A",
    "rodada": "4",
    "data": "2006-05-07",
    "horario": "16h00",
    "time1": "66",
    "time2": "53",
    "placar1": "2",
    "placar2": "0"
  },
  {
    "id": 35,
    "pais": "Brasil",
    "ano": 2006,
    "serie": "A",
    "rodada": "4",
    "data": "2006-05-07",
    "horario": "16h00",
    "time1": "36",
    "time2": "71",
    "placar1": "1",
    "placar2": "2"
  },
  {
    "id": 36,
    "pais": "Brasil",
    "ano": 2006,
    "serie": "A",
    "rodada": "4",
    "data": "2006-05-07",
    "horario": "16h00",
    "time1": "5",
    "time2": "40",
    "placar1": "1",
    "placar2": "2"
  },
  {
    "id": 37,
    "pais": "Brasil",
    "ano": 2006,
    "serie": "A",
    "rodada": "4",
    "data": "2006-05-07",
    "horario": "16h00",
    "time1": "21",
    "time2": "67",
    "placar1": "1",
    "placar2": "3"
  },
  {
    "id": 38,
    "pais": "Brasil",
    "ano": 2006,
    "serie": "A",
    "rodada": "4",
    "data": "2006-05-07",
    "horario": "18h10",
    "time1": "30",
    "time2": "11",
    "placar1": "1",
    "placar2": "0"
  },
  {
    "id": 39,
    "pais": "Brasil",
    "ano": 2006,
    "serie": "A",
    "rodada": "4",
    "data": "2006-05-07",
    "horario": "18h10",
    "time1": "34",
    "time2": "29",
    "placar1": "2",
    "placar2": "1"
  },
  {
    "id": 40,
    "pais": "Brasil",
    "ano": 2006,
    "serie": "A",
    "rodada": "4",
    "data": "2006-05-07",
    "horario": "18h10",
    "time1": "25",
    "time2": "44",
    "placar1": "2",
    "placar2": "0"
  },
  {
    "id": 41,
    "pais": "Brasil",
    "ano": 2006,
    "serie": "A",
    "rodada": "5",
    "data": "2006-05-13",
    "horario": "18h10",
    "time1": "66",
    "time2": "44",
    "placar1": "0",
    "placar2": "2"
  },
  {
    "id": 42,
    "pais": "Brasil",
    "ano": 2006,
    "serie": "A",
    "rodada": "5",
    "data": "2006-05-13",
    "horario": "18h10",
    "time1": "64",
    "time2": "57",
    "placar1": "3",
    "placar2": "1"
  },
  {
    "id": 43,
    "pais": "Brasil",
    "ano": 2006,
    "serie": "A",
    "rodada": "5",
    "data": "2006-05-13",
    "horario": "18h10",
    "time1": "11",
    "time2": "36",
    "placar1": "2",
    "placar2": "2"
  },
  {
    "id": 44,
    "pais": "Brasil",
    "ano": 2006,
    "serie": "A",
    "rodada": "5",
    "data": "2006-05-14",
    "horario": "16h00",
    "time1": "53",
    "time2": "25",
    "placar1": "1",
    "placar2": "1"
  },
  {
    "id": 45,
    "pais": "Brasil",
    "ano": 2006,
    "serie": "A",
    "rodada": "5",
    "data": "2006-05-14",
    "horario": "16h00",
    "time1": "40",
    "time2": "67",
    "placar1": "3",
    "placar2": "1"
  },
  {
    "id": 46,
    "pais": "Brasil",
    "ano": 2006,
    "serie": "A",
    "rodada": "5",
    "data": "2006-05-14",
    "horario": "16h00",
    "time1": "29",
    "time2": "31",
    "placar1": "1",
    "placar2": "0"
  },
  {
    "id": 47,
    "pais": "Brasil",
    "ano": 2006,
    "serie": "A",
    "rodada": "5",
    "data": "2006-05-14",
    "horario": "16h00",
    "time1": "62",
    "time2": "5",
    "placar1": "1",
    "placar2": "2"
  },
  {
    "id": 48,
    "pais": "Brasil",
    "ano": 2006,
    "serie": "A",
    "rodada": "5",
    "data": "2006-05-14",
    "horario": "18h10",
    "time1": "34",
    "time2": "71",
    "placar1": "2",
    "placar2": "0"
  },
  {
    "id": 49,
    "pais": "Brasil",
    "ano": 2006,
    "serie": "A",
    "rodada": "5",
    "data": "2006-05-14",
    "horario": "18h10",
    "time1": "54",
    "time2": "21",
    "placar1": "1",
    "placar2": "2"
  },
  {
    "id": 50,
    "pais": "Brasil",
    "ano": 2006,
    "serie": "A",
    "rodada": "5",
    "data": "2006-05-14",
    "horario": "18h10",
    "time1": "30",
    "time2": "32",
    "placar1": "0",
    "placar2": "0"
  },
  {
    "id": 51,
    "pais": "Brasil",
    "ano": 2006,
    "serie": "A",
    "rodada": "6",
    "data": "2006-05-20",
    "horario": "16h00",
    "time1": "32",
    "time2": "54",
    "placar1": "1",
    "placar2": "1"
  },
  {
    "id": 52,
    "pais": "Brasil",
    "ano": 2006,
    "serie": "A",
    "rodada": "6",
    "data": "2006-05-20",
    "horario": "16h00",
    "time1": "5",
    "time2": "34",
    "placar1": "2",
    "placar2": "3"
  },
  {
    "id": 53,
    "pais": "Brasil",
    "ano": 2006,
    "serie": "A",
    "rodada": "6",
    "data": "2006-05-20",
    "horario": "18h10",
    "time1": "67",
    "time2": "66",
    "placar1": "1",
    "placar2": "0"
  },
  {
    "id": 54,
    "pais": "Brasil",
    "ano": 2006,
    "serie": "A",
    "rodada": "6",
    "data": "2006-05-20",
    "horario": "18h10",
    "time1": "40",
    "time2": "29",
    "placar1": "2",
    "placar2": "4"
  },
  {
    "id": 55,
    "pais": "Brasil",
    "ano": 2006,
    "serie": "A",
    "rodada": "6",
    "data": "2006-05-21",
    "horario": "16h00",
    "time1": "53",
    "time2": "62",
    "placar1": "2",
    "placar2": "1"
  },
  {
    "id": 56,
    "pais": "Brasil",
    "ano": 2006,
    "serie": "A",
    "rodada": "6",
    "data": "2006-05-21",
    "horario": "16h00",
    "time1": "71",
    "time2": "21",
    "placar1": "2",
    "placar2": "4"
  },
  {
    "id": 57,
    "pais": "Brasil",
    "ano": 2006,
    "serie": "A",
    "rodada": "6",
    "data": "2006-05-21",
    "horario": "16h00",
    "time1": "25",
    "time2": "30",
    "placar1": "2",
    "placar2": "1"
  },
  {
    "id": 58,
    "pais": "Brasil",
    "ano": 2006,
    "serie": "A",
    "rodada": "6",
    "data": "2006-05-21",
    "horario": "18h10",
    "time1": "57",
    "time2": "36",
    "placar1": "1",
    "placar2": "1"
  },
  {
    "id": 59,
    "pais": "Brasil",
    "ano": 2006,
    "serie": "A",
    "rodada": "6",
    "data": "2006-05-21",
    "horario": "18h10",
    "time1": "44",
    "time2": "11",
    "placar1": "1",
    "placar2": "0"
  },
  {
    "id": 60,
    "pais": "Brasil",
    "ano": 2006,
    "serie": "A",
    "rodada": "6",
    "data": "2006-05-21",
    "horario": "18h10",
    "time1": "31",
    "time2": "64",
    "placar1": "1",
    "placar2": "0"
  },
  {
    "id": 61,
    "pais": "Brasil",
    "ano": 2006,
    "serie": "A",
    "rodada": "7",
    "data": "2006-05-24",
    "horario": "19h30",
    "time1": "54",
    "time2": "29",
    "placar1": "0",
    "placar2": "0"
  },
  {
    "id": 62,
    "pais": "Brasil",
    "ano": 2006,
    "serie": "A",
    "rodada": "7",
    "data": "2006-05-24",
    "horario": "19h30",
    "time1": "44",
    "time2": "62",
    "placar1": "4",
    "placar2": "1"
  },
  {
    "id": 63,
    "pais": "Brasil",
    "ano": 2006,
    "serie": "A",
    "rodada": "7",
    "data": "2006-05-24",
    "horario": "19h30",
    "time1": "25",
    "time2": "57",
    "placar1": "5",
    "placar2": "1"
  },
  {
    "id": 64,
    "pais": "Brasil",
    "ano": 2006,
    "serie": "A",
    "rodada": "7",
    "data": "2006-05-24",
    "horario": "20h30",
    "time1": "67",
    "time2": "53",
    "placar1": "4",
    "placar2": "1"
  },
  {
    "id": 65,
    "pais": "Brasil",
    "ano": 2006,
    "serie": "A",
    "rodada": "7",
    "data": "2006-05-24",
    "horario": "21h45",
    "time1": "66",
    "time2": "5",
    "placar1": "2",
    "placar2": "1"
  },
  {
    "id": 66,
    "pais": "Brasil",
    "ano": 2006,
    "serie": "A",
    "rodada": "7",
    "data": "2006-05-24",
    "horario": "21h45",
    "time1": "30",
    "time2": "64",
    "placar1": "2",
    "placar2": "2"
  },
  {
    "id": 67,
    "pais": "Brasil",
    "ano": 2006,
    "serie": "A",
    "rodada": "7",
    "data": "2006-05-24",
    "horario": "21h45",
    "time1": "32",
    "time2": "31",
    "placar1": "2",
    "placar2": "5"
  },
  {
    "id": 68,
    "pais": "Brasil",
    "ano": 2006,
    "serie": "A",
    "rodada": "7",
    "data": "2006-05-25",
    "horario": "20h30",
    "time1": "36",
    "time2": "34",
    "placar1": "2",
    "placar2": "0"
  },
  {
    "id": 69,
    "pais": "Brasil",
    "ano": 2006,
    "serie": "A",
    "rodada": "7",
    "data": "2006-05-25",
    "horario": "20h30",
    "time1": "21",
    "time2": "40",
    "placar1": "0",
    "placar2": "1"
  },
  {
    "id": 70,
    "pais": "Brasil",
    "ano": 2006,
    "serie": "A",
    "rodada": "7",
    "data": "2006-05-25",
    "horario": "20h30",
    "time1": "11",
    "time2": "71",
    "placar1": "4",
    "placar2": "1"
  },
  {
    "id": 71,
    "pais": "Brasil",
    "ano": 2006,
    "serie": "A",
    "rodada": "8",
    "data": "2006-05-27",
    "horario": "18h10",
    "time1": "57",
    "time2": "54",
    "placar1": "2",
    "placar2": "5"
  },
  {
    "id": 72,
    "pais": "Brasil",
    "ano": 2006,
    "serie": "A",
    "rodada": "8",
    "data": "2006-05-27",
    "horario": "18h10",
    "time1": "29",
    "time2": "32",
    "placar1": "0",
    "placar2": "0"
  },
  {
    "id": 73,
    "pais": "Brasil",
    "ano": 2006,
    "serie": "A",
    "rodada": "8",
    "data": "2006-05-27",
    "horario": "18h10",
    "time1": "5",
    "time2": "44",
    "placar1": "1",
    "placar2": "0"
  },
  {
    "id": 74,
    "pais": "Brasil",
    "ano": 2006,
    "serie": "A",
    "rodada": "8",
    "data": "2006-05-28",
    "horario": "16h00",
    "time1": "64",
    "time2": "21",
    "placar1": "2",
    "placar2": "0"
  },
  {
    "id": 75,
    "pais": "Brasil",
    "ano": 2006,
    "serie": "A",
    "rodada": "8",
    "data": "2006-05-28",
    "horario": "16h00",
    "time1": "62",
    "time2": "11",
    "placar1": "1",
    "placar2": "1"
  },
  {
    "id": 76,
    "pais": "Brasil",
    "ano": 2006,
    "serie": "A",
    "rodada": "8",
    "data": "2006-05-28",
    "horario": "16h00",
    "time1": "40",
    "time2": "25",
    "placar1": "1",
    "placar2": "1"
  },
  {
    "id": 77,
    "pais": "Brasil",
    "ano": 2006,
    "serie": "A",
    "rodada": "8",
    "data": "2006-05-28",
    "horario": "16h30",
    "time1": "31",
    "time2": "30",
    "placar1": "1",
    "placar2": "0"
  },
  {
    "id": 78,
    "pais": "Brasil",
    "ano": 2006,
    "serie": "A",
    "rodada": "8",
    "data": "2006-05-28",
    "horario": "18h10",
    "time1": "34",
    "time2": "66",
    "placar1": "2",
    "placar2": "1"
  },
  {
    "id": 79,
    "pais": "Brasil",
    "ano": 2006,
    "serie": "A",
    "rodada": "8",
    "data": "2006-05-28",
    "horario": "18h10",
    "time1": "71",
    "time2": "67",
    "placar1": "1",
    "placar2": "1"
  },
  {
    "id": 80,
    "pais": "Brasil",
    "ano": 2006,
    "serie": "A",
    "rodada": "8",
    "data": "2006-05-28",
    "horario": "18h10",
    "time1": "53",
    "time2": "36",
    "placar1": "0",
    "placar2": "1"
  },
  {
    "id": 81,
    "pais": "Brasil",
    "ano": 2006,
    "serie": "A",
    "rodada": "9",
    "data": "2006-05-31",
    "horario": "19h30",
    "time1": "44",
    "time2": "57",
    "placar1": "0",
    "placar2": "1"
  },
  {
    "id": 82,
    "pais": "Brasil",
    "ano": 2006,
    "serie": "A",
    "rodada": "9",
    "data": "2006-05-31",
    "horario": "19h30",
    "time1": "25",
    "time2": "5",
    "placar1": "1",
    "placar2": "1"
  },
  {
    "id": 83,
    "pais": "Brasil",
    "ano": 2006,
    "serie": "A",
    "rodada": "9",
    "data": "2006-05-31",
    "horario": "19h30",
    "time1": "32",
    "time2": "71",
    "placar1": "1",
    "placar2": "1"
  },
  {
    "id": 84,
    "pais": "Brasil",
    "ano": 2006,
    "serie": "A",
    "rodada": "9",
    "data": "2006-05-31",
    "horario": "20h30",
    "time1": "66",
    "time2": "40",
    "placar1": "1",
    "placar2": "1"
  },
  {
    "id": 85,
    "pais": "Brasil",
    "ano": 2006,
    "serie": "A",
    "rodada": "9",
    "data": "2006-05-31",
    "horario": "21h45",
    "time1": "36",
    "time2": "64",
    "placar1": "1",
    "placar2": "0"
  },
  {
    "id": 86,
    "pais": "Brasil",
    "ano": 2006,
    "serie": "A",
    "rodada": "9",
    "data": "2006-05-31",
    "horario": "21h45",
    "time1": "67",
    "time2": "31",
    "placar1": "1",
    "placar2": "0"
  },
  {
    "id": 87,
    "pais": "Brasil",
    "ano": 2006,
    "serie": "A",
    "rodada": "9",
    "data": "2006-05-31",
    "horario": "21h45",
    "time1": "30",
    "time2": "53",
    "placar1": "2",
    "placar2": "1"
  },
  {
    "id": 88,
    "pais": "Brasil",
    "ano": 2006,
    "serie": "A",
    "rodada": "9",
    "data": "2006-06-01",
    "horario": "20h30",
    "time1": "54",
    "time2": "62",
    "placar1": "3",
    "placar2": "0"
  },
  {
    "id": 89,
    "pais": "Brasil",
    "ano": 2006,
    "serie": "A",
    "rodada": "9",
    "data": "2006-06-01",
    "horario": "20h30",
    "time1": "21",
    "time2": "34",
    "placar1": "0",
    "placar2": "1"
  },
  {
    "id": 90,
    "pais": "Brasil",
    "ano": 2006,
    "serie": "A",
    "rodada": "9",
    "data": "2006-06-01",
    "horario": "20h30",
    "time1": "11",
    "time2": "29",
    "placar1": "2",
    "placar2": "3"
  },
  {
    "id": 91,
    "pais": "Brasil",
    "ano": 2006,
    "serie": "A",
    "rodada": "10",
    "data": "2006-06-03",
    "horario": "16h00",
    "time1": "32",
    "time2": "25",
    "placar1": "0",
    "placar2": "2"
  },
  {
    "id": 92,
    "pais": "Brasil",
    "ano": 2006,
    "serie": "A",
    "rodada": "10",
    "data": "2006-06-03",
    "horario": "16h00",
    "time1": "31",
    "time2": "40",
    "placar1": "2",
    "placar2": "3"
  },
  {
    "id": 93,
    "pais": "Brasil",
    "ano": 2006,
    "serie": "A",
    "rodada": "10",
    "data": "2006-06-03",
    "horario": "18h10",
    "time1": "36",
    "time2": "66",
    "placar1": "1",
    "placar2": "1"
  },
  {
    "id": 94,
    "pais": "Brasil",
    "ano": 2006,
    "serie": "A",
    "rodada": "10",
    "data": "2006-06-04",
    "horario": "16h00",
    "time1": "5",
    "time2": "53",
    "placar1": "2",
    "placar2": "0"
  },
  {
    "id": 95,
    "pais": "Brasil",
    "ano": 2006,
    "serie": "A",
    "rodada": "10",
    "data": "2006-06-04",
    "horario": "16h00",
    "time1": "57",
    "time2": "29",
    "placar1": "3",
    "placar2": "0"
  },
  {
    "id": 96,
    "pais": "Brasil",
    "ano": 2006,
    "serie": "A",
    "rodada": "10",
    "data": "2006-06-04",
    "horario": "16h00",
    "time1": "71",
    "time2": "62",
    "placar1": "2",
    "placar2": "1"
  },
  {
    "id": 97,
    "pais": "Brasil",
    "ano": 2006,
    "serie": "A",
    "rodada": "10",
    "data": "2006-06-04",
    "horario": "16h00",
    "time1": "21",
    "time2": "30",
    "placar1": "0",
    "placar2": "2"
  },
  {
    "id": 98,
    "pais": "Brasil",
    "ano": 2006,
    "serie": "A",
    "rodada": "10",
    "data": "2006-06-04",
    "horario": "18h10",
    "time1": "64",
    "time2": "11",
    "placar1": "0",
    "placar2": "0"
  },
  {
    "id": 99,
    "pais": "Brasil",
    "ano": 2006,
    "serie": "A",
    "rodada": "10",
    "data": "2006-06-04",
    "horario": "18h10",
    "time1": "44",
    "time2": "67",
    "placar1": "1",
    "placar2": "1"
  },
  {
    "id": 100,
    "pais": "Brasil",
    "ano": 2006,
    "serie": "A",
    "rodada": "10",
    "data": "2006-06-04",
    "horario": "18h10",
    "time1": "34",
    "time2": "54",
    "placar1": "1",
    "placar2": "2"
  },
  {
    "id": 101,
    "pais": "Brasil",
    "ano": 2006,
    "serie": "A",
    "rodada": "11",
    "data": "2006-07-12",
    "horario": "19h30",
    "time1": "31",
    "time2": "44",
    "placar1": "3",
    "placar2": "2"
  },
  {
    "id": 102,
    "pais": "Brasil",
    "ano": 2006,
    "serie": "A",
    "rodada": "11",
    "data": "2006-07-12",
    "horario": "19h30",
    "time1": "40",
    "time2": "57",
    "placar1": "2",
    "placar2": "0"
  },
  {
    "id": 103,
    "pais": "Brasil",
    "ano": 2006,
    "serie": "A",
    "rodada": "11",
    "data": "2006-07-12",
    "horario": "19h30",
    "time1": "5",
    "time2": "32",
    "placar1": "0",
    "placar2": "0"
  },
  {
    "id": 104,
    "pais": "Brasil",
    "ano": 2006,
    "serie": "A",
    "rodada": "11",
    "data": "2006-07-12",
    "horario": "20h30",
    "time1": "67",
    "time2": "36",
    "placar1": "2",
    "placar2": "1"
  },
  {
    "id": 105,
    "pais": "Brasil",
    "ano": 2006,
    "serie": "A",
    "rodada": "11",
    "data": "2006-07-12",
    "horario": "21h45",
    "time1": "66",
    "time2": "11",
    "placar1": "1",
    "placar2": "1"
  },
  {
    "id": 106,
    "pais": "Brasil",
    "ano": 2006,
    "serie": "A",
    "rodada": "11",
    "data": "2006-07-12",
    "horario": "21h45",
    "time1": "25",
    "time2": "21",
    "placar1": "2",
    "placar2": "0"
  },
  {
    "id": 107,
    "pais": "Brasil",
    "ano": 2006,
    "serie": "A",
    "rodada": "11",
    "data": "2006-07-12",
    "horario": "21h45",
    "time1": "29",
    "time2": "64",
    "placar1": "2",
    "placar2": "1"
  },
  {
    "id": 108,
    "pais": "Brasil",
    "ano": 2006,
    "serie": "A",
    "rodada": "11",
    "data": "2006-07-13",
    "horario": "20h30",
    "time1": "62",
    "time2": "34",
    "placar1": "2",
    "placar2": "1"
  },
  {
    "id": 109,
    "pais": "Brasil",
    "ano": 2006,
    "serie": "A",
    "rodada": "11",
    "data": "2006-07-13",
    "horario": "20h30",
    "time1": "30",
    "time2": "54",
    "placar1": "1",
    "placar2": "4"
  },
  {
    "id": 110,
    "pais": "Brasil",
    "ano": 2006,
    "serie": "A",
    "rodada": "11",
    "data": "2006-07-13",
    "horario": "20h30",
    "time1": "53",
    "time2": "71",
    "placar1": "4",
    "placar2": "2"
  },
  {
    "id": 111,
    "pais": "Brasil",
    "ano": 2006,
    "serie": "A",
    "rodada": "12",
    "data": "2006-07-15",
    "horario": "16h00",
    "time1": "11",
    "time2": "57",
    "placar1": "4",
    "placar2": "1"
  },
  {
    "id": 112,
    "pais": "Brasil",
    "ano": 2006,
    "serie": "A",
    "rodada": "12",
    "data": "2006-07-15",
    "horario": "18h10",
    "time1": "67",
    "time2": "29",
    "placar1": "2",
    "placar2": "1"
  },
  {
    "id": 113,
    "pais": "Brasil",
    "ano": 2006,
    "serie": "A",
    "rodada": "12",
    "data": "2006-07-16",
    "horario": "16h00",
    "time1": "53",
    "time2": "21",
    "placar1": "1",
    "placar2": "0"
  },
  {
    "id": 114,
    "pais": "Brasil",
    "ano": 2006,
    "serie": "A",
    "rodada": "12",
    "data": "2006-07-16",
    "horario": "16h00",
    "time1": "66",
    "time2": "64",
    "placar1": "2",
    "placar2": "0"
  },
  {
    "id": 115,
    "pais": "Brasil",
    "ano": 2006,
    "serie": "A",
    "rodada": "12",
    "data": "2006-07-16",
    "horario": "16h00",
    "time1": "36",
    "time2": "31",
    "placar1": "4",
    "placar2": "4"
  },
  {
    "id": 116,
    "pais": "Brasil",
    "ano": 2006,
    "serie": "A",
    "rodada": "12",
    "data": "2006-07-16",
    "horario": "16h00",
    "time1": "25",
    "time2": "34",
    "placar1": "0",
    "placar2": "0"
  },
  {
    "id": 117,
    "pais": "Brasil",
    "ano": 2006,
    "serie": "A",
    "rodada": "12",
    "data": "2006-07-16",
    "horario": "18h10",
    "time1": "44",
    "time2": "40",
    "placar1": "2",
    "placar2": "0"
  },
  {
    "id": 118,
    "pais": "Brasil",
    "ano": 2006,
    "serie": "A",
    "rodada": "12",
    "data": "2006-07-16",
    "horario": "18h10",
    "time1": "54",
    "time2": "5",
    "placar1": "2",
    "placar2": "1"
  },
  {
    "id": 119,
    "pais": "Brasil",
    "ano": 2006,
    "serie": "A",
    "rodada": "12",
    "data": "2006-07-16",
    "horario": "18h10",
    "time1": "30",
    "time2": "71",
    "placar1": "0",
    "placar2": "1"
  },
  {
    "id": 120,
    "pais": "Brasil",
    "ano": 2006,
    "serie": "A",
    "rodada": "12",
    "data": "2006-07-16",
    "horario": "18h10",
    "time1": "32",
    "time2": "62",
    "placar1": "1",
    "placar2": "4"
  },
  {
    "id": 121,
    "pais": "Brasil",
    "ano": 2006,
    "serie": "A",
    "rodada": "13",
    "data": "2006-07-22",
    "horario": "16h00",
    "time1": "54",
    "time2": "25",
    "placar1": "1",
    "placar2": "0"
  },
  {
    "id": 122,
    "pais": "Brasil",
    "ano": 2006,
    "serie": "A",
    "rodada": "13",
    "data": "2006-07-22",
    "horario": "16h00",
    "time1": "29",
    "time2": "36",
    "placar1": "2",
    "placar2": "0"
  },
  {
    "id": 123,
    "pais": "Brasil",
    "ano": 2006,
    "serie": "A",
    "rodada": "13",
    "data": "2006-07-22",
    "horario": "18h10",
    "time1": "31",
    "time2": "66",
    "placar1": "2",
    "placar2": "2"
  },
  {
    "id": 124,
    "pais": "Brasil",
    "ano": 2006,
    "serie": "A",
    "rodada": "13",
    "data": "2006-07-22",
    "horario": "18h10",
    "time1": "21",
    "time2": "32",
    "placar1": "2",
    "placar2": "2"
  },
  {
    "id": 125,
    "pais": "Brasil",
    "ano": 2006,
    "serie": "A",
    "rodada": "13",
    "data": "2006-07-23",
    "horario": "16h00",
    "time1": "71",
    "time2": "5",
    "placar1": "2",
    "placar2": "1"
  },
  {
    "id": 126,
    "pais": "Brasil",
    "ano": 2006,
    "serie": "A",
    "rodada": "13",
    "data": "2006-07-23",
    "horario": "16h00",
    "time1": "62",
    "time2": "30",
    "placar1": "3",
    "placar2": "0"
  },
  {
    "id": 127,
    "pais": "Brasil",
    "ano": 2006,
    "serie": "A",
    "rodada": "13",
    "data": "2006-07-23",
    "horario": "16h00",
    "time1": "57",
    "time2": "67",
    "placar1": "1",
    "placar2": "3"
  },
  {
    "id": 128,
    "pais": "Brasil",
    "ano": 2006,
    "serie": "A",
    "rodada": "13",
    "data": "2006-07-23",
    "horario": "18h10",
    "time1": "64",
    "time2": "44",
    "placar1": "3",
    "placar2": "2"
  },
  {
    "id": 129,
    "pais": "Brasil",
    "ano": 2006,
    "serie": "A",
    "rodada": "13",
    "data": "2006-07-23",
    "horario": "18h10",
    "time1": "40",
    "time2": "11",
    "placar1": "0",
    "placar2": "0"
  },
  {
    "id": 130,
    "pais": "Brasil",
    "ano": 2006,
    "serie": "A",
    "rodada": "13",
    "data": "2006-07-23",
    "horario": "18h10",
    "time1": "34",
    "time2": "53",
    "placar1": "1",
    "placar2": "3"
  },
  {
    "id": 131,
    "pais": "Brasil",
    "ano": 2006,
    "serie": "A",
    "rodada": "14",
    "data": "2006-07-29",
    "horario": "16h00",
    "time1": "44",
    "time2": "29",
    "placar1": "1",
    "placar2": "0"
  },
  {
    "id": 132,
    "pais": "Brasil",
    "ano": 2006,
    "serie": "A",
    "rodada": "14",
    "data": "2006-07-29",
    "horario": "18h10",
    "time1": "66",
    "time2": "57",
    "placar1": "1",
    "placar2": "1"
  },
  {
    "id": 133,
    "pais": "Brasil",
    "ano": 2006,
    "serie": "A",
    "rodada": "14",
    "data": "2006-07-29",
    "horario": "18h10",
    "time1": "53",
    "time2": "54",
    "placar1": "4",
    "placar2": "2"
  },
  {
    "id": 134,
    "pais": "Brasil",
    "ano": 2006,
    "serie": "A",
    "rodada": "14",
    "data": "2006-07-30",
    "horario": "16h00",
    "time1": "71",
    "time2": "25",
    "placar1": "1",
    "placar2": "0"
  },
  {
    "id": 135,
    "pais": "Brasil",
    "ano": 2006,
    "serie": "A",
    "rodada": "14",
    "data": "2006-07-30",
    "horario": "16h00",
    "time1": "5",
    "time2": "30",
    "placar1": "1",
    "placar2": "0"
  },
  {
    "id": 136,
    "pais": "Brasil",
    "ano": 2006,
    "serie": "A",
    "rodada": "14",
    "data": "2006-07-30",
    "horario": "16h00",
    "time1": "67",
    "time2": "64",
    "placar1": "0",
    "placar2": "4"
  },
  {
    "id": 137,
    "pais": "Brasil",
    "ano": 2006,
    "serie": "A",
    "rodada": "14",
    "data": "2006-07-30",
    "horario": "16h00",
    "time1": "62",
    "time2": "21",
    "placar1": "1",
    "placar2": "0"
  },
  {
    "id": 138,
    "pais": "Brasil",
    "ano": 2006,
    "serie": "A",
    "rodada": "14",
    "data": "2006-07-30",
    "horario": "18h10",
    "time1": "34",
    "time2": "32",
    "placar1": "1",
    "placar2": "1"
  },
  {
    "id": 139,
    "pais": "Brasil",
    "ano": 2006,
    "serie": "A",
    "rodada": "14",
    "data": "2006-07-30",
    "horario": "18h10",
    "time1": "40",
    "time2": "36",
    "placar1": "0",
    "placar2": "0"
  },
  {
    "id": 140,
    "pais": "Brasil",
    "ano": 2006,
    "serie": "A",
    "rodada": "14",
    "data": "2006-07-30",
    "horario": "18h10",
    "time1": "31",
    "time2": "11",
    "placar1": "1",
    "placar2": "1"
  },
  {
    "id": 141,
    "pais": "Brasil",
    "ano": 2006,
    "serie": "A",
    "rodada": "15",
    "data": "2006-08-05",
    "horario": "16h00",
    "time1": "36",
    "time2": "44",
    "placar1": "1",
    "placar2": "0"
  },
  {
    "id": 142,
    "pais": "Brasil",
    "ano": 2006,
    "serie": "A",
    "rodada": "15",
    "data": "2006-08-05",
    "horario": "16h00",
    "time1": "29",
    "time2": "66",
    "placar1": "1",
    "placar2": "1"
  },
  {
    "id": 143,
    "pais": "Brasil",
    "ano": 2006,
    "serie": "A",
    "rodada": "15",
    "data": "2006-08-05",
    "horario": "18h10",
    "time1": "30",
    "time2": "34",
    "placar1": "1",
    "placar2": "0"
  },
  {
    "id": 144,
    "pais": "Brasil",
    "ano": 2006,
    "serie": "A",
    "rodada": "15",
    "data": "2006-08-05",
    "horario": "18h10",
    "time1": "21",
    "time2": "5",
    "placar1": "2",
    "placar2": "1"
  },
  {
    "id": 145,
    "pais": "Brasil",
    "ano": 2006,
    "serie": "A",
    "rodada": "15",
    "data": "2006-08-06",
    "horario": "16h00",
    "time1": "64",
    "time2": "40",
    "placar1": "2",
    "placar2": "1"
  },
  {
    "id": 146,
    "pais": "Brasil",
    "ano": 2006,
    "serie": "A",
    "rodada": "15",
    "data": "2006-08-06",
    "horario": "16h00",
    "time1": "54",
    "time2": "71",
    "placar1": "2",
    "placar2": "1"
  },
  {
    "id": 147,
    "pais": "Brasil",
    "ano": 2006,
    "serie": "A",
    "rodada": "15",
    "data": "2006-08-06",
    "horario": "16h00",
    "time1": "11",
    "time2": "67",
    "placar1": "1",
    "placar2": "1"
  },
  {
    "id": 148,
    "pais": "Brasil",
    "ano": 2006,
    "serie": "A",
    "rodada": "15",
    "data": "2006-08-06",
    "horario": "18h10",
    "time1": "32",
    "time2": "53",
    "placar1": "0",
    "placar2": "0"
  },
  {
    "id": 149,
    "pais": "Brasil",
    "ano": 2006,
    "serie": "A",
    "rodada": "15",
    "data": "2006-08-06",
    "horario": "18h10",
    "time1": "57",
    "time2": "31",
    "placar1": "3",
    "placar2": "0"
  },
  {
    "id": 150,
    "pais": "Brasil",
    "ano": 2006,
    "serie": "A",
    "rodada": "15",
    "data": "2006-08-06",
    "horario": "18h10",
    "time1": "25",
    "time2": "62",
    "placar1": "3",
    "placar2": "3"
  },
  {
    "id": 151,
    "pais": "Brasil",
    "ano": 2006,
    "serie": "A",
    "rodada": "16",
    "data": "2006-08-12",
    "horario": "16h00",
    "time1": "66",
    "time2": "62",
    "placar1": "2",
    "placar2": "0"
  },
  {
    "id": 152,
    "pais": "Brasil",
    "ano": 2006,
    "serie": "A",
    "rodada": "16",
    "data": "2006-08-12",
    "horario": "16h00",
    "time1": "44",
    "time2": "71",
    "placar1": "0",
    "placar2": "0"
  },
  {
    "id": 153,
    "pais": "Brasil",
    "ano": 2006,
    "serie": "A",
    "rodada": "16",
    "data": "2006-08-12",
    "horario": "18h10",
    "time1": "30",
    "time2": "57",
    "placar1": "0",
    "placar2": "0"
  },
  {
    "id": 154,
    "pais": "Brasil",
    "ano": 2006,
    "serie": "A",
    "rodada": "16",
    "data": "2006-08-12",
    "horario": "18h10",
    "time1": "21",
    "time2": "29",
    "placar1": "1",
    "placar2": "3"
  },
  {
    "id": 155,
    "pais": "Brasil",
    "ano": 2006,
    "serie": "A",
    "rodada": "16",
    "data": "2006-08-13",
    "horario": "16h00",
    "time1": "36",
    "time2": "5",
    "placar1": "2",
    "placar2": "0"
  },
  {
    "id": 156,
    "pais": "Brasil",
    "ano": 2006,
    "serie": "A",
    "rodada": "16",
    "data": "2006-08-13",
    "horario": "16h00",
    "time1": "11",
    "time2": "53",
    "placar1": "1",
    "placar2": "3"
  },
  {
    "id": 157,
    "pais": "Brasil",
    "ano": 2006,
    "serie": "A",
    "rodada": "16",
    "data": "2006-08-13",
    "horario": "16h00",
    "time1": "25",
    "time2": "31",
    "placar1": "2",
    "placar2": "3"
  },
  {
    "id": 158,
    "pais": "Brasil",
    "ano": 2006,
    "serie": "A",
    "rodada": "16",
    "data": "2006-08-13",
    "horario": "18h10",
    "time1": "67",
    "time2": "34",
    "placar1": "2",
    "placar2": "1"
  },
  {
    "id": 159,
    "pais": "Brasil",
    "ano": 2006,
    "serie": "A",
    "rodada": "16",
    "data": "2006-08-13",
    "horario": "18h10",
    "time1": "54",
    "time2": "64",
    "placar1": "1",
    "placar2": "1"
  },
  {
    "id": 160,
    "pais": "Brasil",
    "ano": 2006,
    "serie": "A",
    "rodada": "16",
    "data": "2006-08-13",
    "horario": "18h10",
    "time1": "32",
    "time2": "40",
    "placar1": "1",
    "placar2": "2"
  },
  {
    "id": 161,
    "pais": "Brasil",
    "ano": 2006,
    "serie": "A",
    "rodada": "17",
    "data": "2006-08-16",
    "horario": "19h30",
    "time1": "62",
    "time2": "36",
    "placar1": "2",
    "placar2": "4"
  },
  {
    "id": 162,
    "pais": "Brasil",
    "ano": 2006,
    "serie": "A",
    "rodada": "17",
    "data": "2006-08-16",
    "horario": "19h30",
    "time1": "71",
    "time2": "66",
    "placar1": "1",
    "placar2": "2"
  },
  {
    "id": 163,
    "pais": "Brasil",
    "ano": 2006,
    "serie": "A",
    "rodada": "17",
    "data": "2006-08-16",
    "horario": "19h30",
    "time1": "57",
    "time2": "32",
    "placar1": "1",
    "placar2": "3"
  },
  {
    "id": 164,
    "pais": "Brasil",
    "ano": 2006,
    "serie": "A",
    "rodada": "17",
    "data": "2006-08-16",
    "horario": "20h30",
    "time1": "34",
    "time2": "11",
    "placar1": "2",
    "placar2": "2"
  },
  {
    "id": 165,
    "pais": "Brasil",
    "ano": 2006,
    "serie": "A",
    "rodada": "17",
    "data": "2006-08-16",
    "horario": "22h00",
    "time1": "31",
    "time2": "21",
    "placar1": "1",
    "placar2": "2"
  },
  {
    "id": 166,
    "pais": "Brasil",
    "ano": 2006,
    "serie": "A",
    "rodada": "17",
    "data": "2006-08-16",
    "horario": "22h00",
    "time1": "29",
    "time2": "30",
    "placar1": "1",
    "placar2": "1"
  },
  {
    "id": 167,
    "pais": "Brasil",
    "ano": 2006,
    "serie": "A",
    "rodada": "17",
    "data": "2006-08-17",
    "horario": "20h30",
    "time1": "53",
    "time2": "44",
    "placar1": "1",
    "placar2": "1"
  },
  {
    "id": 168,
    "pais": "Brasil",
    "ano": 2006,
    "serie": "A",
    "rodada": "17",
    "data": "2006-08-17",
    "horario": "20h30",
    "time1": "64",
    "time2": "25",
    "placar1": "2",
    "placar2": "0"
  },
  {
    "id": 169,
    "pais": "Brasil",
    "ano": 2006,
    "serie": "A",
    "rodada": "18",
    "data": "2006-08-19",
    "horario": "16h00",
    "time1": "57",
    "time2": "34",
    "placar1": "3",
    "placar2": "2"
  },
  {
    "id": 170,
    "pais": "Brasil",
    "ano": 2006,
    "serie": "A",
    "rodada": "18",
    "data": "2006-08-19",
    "horario": "18h10",
    "time1": "30",
    "time2": "36",
    "placar1": "1",
    "placar2": "0"
  },
  {
    "id": 171,
    "pais": "Brasil",
    "ano": 2006,
    "serie": "A",
    "rodada": "18",
    "data": "2006-08-20",
    "horario": "16h00",
    "time1": "64",
    "time2": "71",
    "placar1": "0",
    "placar2": "2"
  },
  {
    "id": 172,
    "pais": "Brasil",
    "ano": 2006,
    "serie": "A",
    "rodada": "18",
    "data": "2006-08-20",
    "horario": "16h00",
    "time1": "32",
    "time2": "44",
    "placar1": "4",
    "placar2": "1"
  },
  {
    "id": 173,
    "pais": "Brasil",
    "ano": 2006,
    "serie": "A",
    "rodada": "18",
    "data": "2006-08-20",
    "horario": "16h00",
    "time1": "31",
    "time2": "62",
    "placar1": "1",
    "placar2": "1"
  },
  {
    "id": 174,
    "pais": "Brasil",
    "ano": 2006,
    "serie": "A",
    "rodada": "18",
    "data": "2006-08-20",
    "horario": "16h00",
    "time1": "25",
    "time2": "67",
    "placar1": "2",
    "placar2": "2"
  },
  {
    "id": 175,
    "pais": "Brasil",
    "ano": 2006,
    "serie": "A",
    "rodada": "18",
    "data": "2006-08-20",
    "horario": "18h10",
    "time1": "40",
    "time2": "53",
    "placar1": "1",
    "placar2": "1"
  },
  {
    "id": 176,
    "pais": "Brasil",
    "ano": 2006,
    "serie": "A",
    "rodada": "18",
    "data": "2006-08-20",
    "horario": "18h10",
    "time1": "29",
    "time2": "5",
    "placar1": "3",
    "placar2": "3"
  },
  {
    "id": 177,
    "pais": "Brasil",
    "ano": 2006,
    "serie": "A",
    "rodada": "18",
    "data": "2006-08-20",
    "horario": "18h10",
    "time1": "54",
    "time2": "66",
    "placar1": "1",
    "placar2": "0"
  },
  {
    "id": 178,
    "pais": "Brasil",
    "ano": 2006,
    "serie": "A",
    "rodada": "18",
    "data": "2006-08-20",
    "horario": "18h10",
    "time1": "21",
    "time2": "11",
    "placar1": "1",
    "placar2": "0"
  },
  {
    "id": 179,
    "pais": "Brasil",
    "ano": 2006,
    "serie": "A",
    "rodada": "19",
    "data": "2006-08-23",
    "horario": "19h30",
    "time1": "53",
    "time2": "31",
    "placar1": "3",
    "placar2": "0"
  },
  {
    "id": 180,
    "pais": "Brasil",
    "ano": 2006,
    "serie": "A",
    "rodada": "19",
    "data": "2006-08-23",
    "horario": "19h30",
    "time1": "34",
    "time2": "40",
    "placar1": "2",
    "placar2": "2"
  },
  {
    "id": 181,
    "pais": "Brasil",
    "ano": 2006,
    "serie": "A",
    "rodada": "19",
    "data": "2006-08-23",
    "horario": "19h30",
    "time1": "5",
    "time2": "57",
    "placar1": "3",
    "placar2": "0"
  },
  {
    "id": 182,
    "pais": "Brasil",
    "ano": 2006,
    "serie": "A",
    "rodada": "19",
    "data": "2006-08-23",
    "horario": "20h30",
    "time1": "11",
    "time2": "25",
    "placar1": "1",
    "placar2": "0"
  },
  {
    "id": 183,
    "pais": "Brasil",
    "ano": 2006,
    "serie": "A",
    "rodada": "19",
    "data": "2006-08-23",
    "horario": "22h00",
    "time1": "44",
    "time2": "21",
    "placar1": "0",
    "placar2": "0"
  },
  {
    "id": 184,
    "pais": "Brasil",
    "ano": 2006,
    "serie": "A",
    "rodada": "19",
    "data": "2006-08-23",
    "horario": "22h00",
    "time1": "66",
    "time2": "30",
    "placar1": "2",
    "placar2": "2"
  },
  {
    "id": 185,
    "pais": "Brasil",
    "ano": 2006,
    "serie": "A",
    "rodada": "19",
    "data": "2006-08-23",
    "horario": "22h00",
    "time1": "62",
    "time2": "64",
    "placar1": "1",
    "placar2": "1"
  },
  {
    "id": 186,
    "pais": "Brasil",
    "ano": 2006,
    "serie": "A",
    "rodada": "19",
    "data": "2006-08-24",
    "horario": "20h30",
    "time1": "67",
    "time2": "54",
    "placar1": "3",
    "placar2": "2"
  },
  {
    "id": 187,
    "pais": "Brasil",
    "ano": 2006,
    "serie": "A",
    "rodada": "19",
    "data": "2006-08-24",
    "horario": "20h30",
    "time1": "71",
    "time2": "29",
    "placar1": "3",
    "placar2": "1"
  },
  {
    "id": 188,
    "pais": "Brasil",
    "ano": 2006,
    "serie": "A",
    "rodada": "19",
    "data": "2006-08-24",
    "horario": "20h30",
    "time1": "36",
    "time2": "32",
    "placar1": "4",
    "placar2": "1"
  },
  {
    "id": 189,
    "pais": "Brasil",
    "ano": 2006,
    "serie": "A",
    "rodada": "20",
    "data": "2006-08-26",
    "horario": "16h00",
    "time1": "31",
    "time2": "5",
    "placar1": "1",
    "placar2": "2"
  },
  {
    "id": 190,
    "pais": "Brasil",
    "ano": 2006,
    "serie": "A",
    "rodada": "20",
    "data": "2006-08-26",
    "horario": "18h10",
    "time1": "25",
    "time2": "66",
    "placar1": "3",
    "placar2": "0"
  },
  {
    "id": 191,
    "pais": "Brasil",
    "ano": 2006,
    "serie": "A",
    "rodada": "20",
    "data": "2006-08-26",
    "horario": "18h10",
    "time1": "64",
    "time2": "34",
    "placar1": "2",
    "placar2": "1"
  },
  {
    "id": 192,
    "pais": "Brasil",
    "ano": 2006,
    "serie": "A",
    "rodada": "20",
    "data": "2006-08-27",
    "horario": "16h00",
    "time1": "30",
    "time2": "67",
    "placar1": "1",
    "placar2": "1"
  },
  {
    "id": 193,
    "pais": "Brasil",
    "ano": 2006,
    "serie": "A",
    "rodada": "20",
    "data": "2006-08-27",
    "horario": "16h00",
    "time1": "54",
    "time2": "44",
    "placar1": "0",
    "placar2": "1"
  },
  {
    "id": 194,
    "pais": "Brasil",
    "ano": 2006,
    "serie": "A",
    "rodada": "20",
    "data": "2006-08-27",
    "horario": "16h00",
    "time1": "40",
    "time2": "71",
    "placar1": "1",
    "placar2": "2"
  },
  {
    "id": 195,
    "pais": "Brasil",
    "ano": 2006,
    "serie": "A",
    "rodada": "20",
    "data": "2006-08-27",
    "horario": "16h00",
    "time1": "21",
    "time2": "36",
    "placar1": "0",
    "placar2": "2"
  },
  {
    "id": 196,
    "pais": "Brasil",
    "ano": 2006,
    "serie": "A",
    "rodada": "20",
    "data": "2006-08-27",
    "horario": "18h10",
    "time1": "32",
    "time2": "11",
    "placar1": "2",
    "placar2": "3"
  },
  {
    "id": 197,
    "pais": "Brasil",
    "ano": 2006,
    "serie": "A",
    "rodada": "20",
    "data": "2006-08-27",
    "horario": "18h10",
    "time1": "57",
    "time2": "53",
    "placar1": "1",
    "placar2": "1"
  },
  {
    "id": 198,
    "pais": "Brasil",
    "ano": 2006,
    "serie": "A",
    "rodada": "20",
    "data": "2006-08-27",
    "horario": "18h10",
    "time1": "29",
    "time2": "62",
    "placar1": "2",
    "placar2": "0"
  },
  {
    "id": 199,
    "pais": "Brasil",
    "ano": 2006,
    "serie": "A",
    "rodada": "21",
    "data": "2006-08-30",
    "horario": "19h30",
    "time1": "34",
    "time2": "31",
    "placar1": "3",
    "placar2": "1"
  },
  {
    "id": 200,
    "pais": "Brasil",
    "ano": 2006,
    "serie": "A",
    "rodada": "21",
    "data": "2006-08-30",
    "horario": "19h30",
    "time1": "62",
    "time2": "40",
    "placar1": "0",
    "placar2": "2"
  },
  {
    "id": 201,
    "pais": "Brasil",
    "ano": 2006,
    "serie": "A",
    "rodada": "21",
    "data": "2006-08-30",
    "horario": "19h30",
    "time1": "36",
    "time2": "25",
    "placar1": "2",
    "placar2": "1"
  },
  {
    "id": 202,
    "pais": "Brasil",
    "ano": 2006,
    "serie": "A",
    "rodada": "21",
    "data": "2006-08-30",
    "horario": "20h30",
    "time1": "53",
    "time2": "29",
    "placar1": "1",
    "placar2": "1"
  },
  {
    "id": 203,
    "pais": "Brasil",
    "ano": 2006,
    "serie": "A",
    "rodada": "21",
    "data": "2006-08-30",
    "horario": "22h00",
    "time1": "66",
    "time2": "21",
    "placar1": "0",
    "placar2": "1"
  },
  {
    "id": 204,
    "pais": "Brasil",
    "ano": 2006,
    "serie": "A",
    "rodada": "21",
    "data": "2006-08-30",
    "horario": "22h00",
    "time1": "44",
    "time2": "30",
    "placar1": "1",
    "placar2": "0"
  },
  {
    "id": 205,
    "pais": "Brasil",
    "ano": 2006,
    "serie": "A",
    "rodada": "21",
    "data": "2006-08-30",
    "horario": "22h00",
    "time1": "5",
    "time2": "64",
    "placar1": "2",
    "placar2": "1"
  },
  {
    "id": 206,
    "pais": "Brasil",
    "ano": 2006,
    "serie": "A",
    "rodada": "21",
    "data": "2006-08-31",
    "horario": "20h30",
    "time1": "67",
    "time2": "32",
    "placar1": "1",
    "placar2": "1"
  },
  {
    "id": 207,
    "pais": "Brasil",
    "ano": 2006,
    "serie": "A",
    "rodada": "21",
    "data": "2006-08-31",
    "horario": "20h30",
    "time1": "71",
    "time2": "57",
    "placar1": "2",
    "placar2": "2"
  },
  {
    "id": 208,
    "pais": "Brasil",
    "ano": 2006,
    "serie": "A",
    "rodada": "21",
    "data": "2006-08-31",
    "horario": "20h30",
    "time1": "11",
    "time2": "54",
    "placar1": "4",
    "placar2": "0"
  },
  {
    "id": 209,
    "pais": "Brasil",
    "ano": 2006,
    "serie": "A",
    "rodada": "22",
    "data": "2006-09-02",
    "horario": "16h00",
    "time1": "25",
    "time2": "29",
    "placar1": "2",
    "placar2": "2"
  },
  {
    "id": 210,
    "pais": "Brasil",
    "ano": 2006,
    "serie": "A",
    "rodada": "22",
    "data": "2006-09-02",
    "horario": "18h10",
    "time1": "30",
    "time2": "40",
    "placar1": "1",
    "placar2": "2"
  },
  {
    "id": 211,
    "pais": "Brasil",
    "ano": 2006,
    "serie": "A",
    "rodada": "22",
    "data": "2006-09-03",
    "horario": "16h00",
    "time1": "34",
    "time2": "44",
    "placar1": "2",
    "placar2": "0"
  },
  {
    "id": 212,
    "pais": "Brasil",
    "ano": 2006,
    "serie": "A",
    "rodada": "22",
    "data": "2006-09-03",
    "horario": "16h00",
    "time1": "64",
    "time2": "53",
    "placar1": "5",
    "placar2": "1"
  },
  {
    "id": 213,
    "pais": "Brasil",
    "ano": 2006,
    "serie": "A",
    "rodada": "22",
    "data": "2006-09-03",
    "horario": "16h00",
    "time1": "66",
    "time2": "32",
    "placar1": "0",
    "placar2": "0"
  },
  {
    "id": 214,
    "pais": "Brasil",
    "ano": 2006,
    "serie": "A",
    "rodada": "22",
    "data": "2006-09-03",
    "horario": "16h00",
    "time1": "36",
    "time2": "54",
    "placar1": "2",
    "placar2": "1"
  },
  {
    "id": 215,
    "pais": "Brasil",
    "ano": 2006,
    "serie": "A",
    "rodada": "22",
    "data": "2006-09-03",
    "horario": "16h00",
    "time1": "5",
    "time2": "11",
    "placar1": "0",
    "placar2": "5"
  },
  {
    "id": 216,
    "pais": "Brasil",
    "ano": 2006,
    "serie": "A",
    "rodada": "22",
    "data": "2006-09-03",
    "horario": "18h10",
    "time1": "21",
    "time2": "57",
    "placar1": "1",
    "placar2": "0"
  },
  {
    "id": 217,
    "pais": "Brasil",
    "ano": 2006,
    "serie": "A",
    "rodada": "22",
    "data": "2006-09-03",
    "horario": "18h10",
    "time1": "62",
    "time2": "67",
    "placar1": "1",
    "placar2": "3"
  },
  {
    "id": 218,
    "pais": "Brasil",
    "ano": 2006,
    "serie": "A",
    "rodada": "22",
    "data": "2006-09-03",
    "horario": "18h10",
    "time1": "31",
    "time2": "71",
    "placar1": "1",
    "placar2": "1"
  },
  {
    "id": 219,
    "pais": "Brasil",
    "ano": 2006,
    "serie": "A",
    "rodada": "23",
    "data": "2006-09-09",
    "horario": "16h00",
    "time1": "57",
    "time2": "62",
    "placar1": "2",
    "placar2": "0"
  },
  {
    "id": 220,
    "pais": "Brasil",
    "ano": 2006,
    "serie": "A",
    "rodada": "23",
    "data": "2006-09-09",
    "horario": "18h10",
    "time1": "53",
    "time2": "66",
    "placar1": "3",
    "placar2": "1"
  },
  {
    "id": 221,
    "pais": "Brasil",
    "ano": 2006,
    "serie": "A",
    "rodada": "23",
    "data": "2006-09-09",
    "horario": "18h10",
    "time1": "71",
    "time2": "36",
    "placar1": "1",
    "placar2": "1"
  },
  {
    "id": 222,
    "pais": "Brasil",
    "ano": 2006,
    "serie": "A",
    "rodada": "23",
    "data": "2006-09-10",
    "horario": "16h00",
    "time1": "67",
    "time2": "21",
    "placar1": "0",
    "placar2": "0"
  },
  {
    "id": 223,
    "pais": "Brasil",
    "ano": 2006,
    "serie": "A",
    "rodada": "23",
    "data": "2006-09-10",
    "horario": "16h00",
    "time1": "54",
    "time2": "31",
    "placar1": "1",
    "placar2": "0"
  },
  {
    "id": 224,
    "pais": "Brasil",
    "ano": 2006,
    "serie": "A",
    "rodada": "23",
    "data": "2006-09-10",
    "horario": "16h00",
    "time1": "44",
    "time2": "25",
    "placar1": "2",
    "placar2": "0"
  },
  {
    "id": 225,
    "pais": "Brasil",
    "ano": 2006,
    "serie": "A",
    "rodada": "23",
    "data": "2006-09-10",
    "horario": "16h00",
    "time1": "29",
    "time2": "34",
    "placar1": "2",
    "placar2": "2"
  },
  {
    "id": 226,
    "pais": "Brasil",
    "ano": 2006,
    "serie": "A",
    "rodada": "23",
    "data": "2006-09-10",
    "horario": "18h10",
    "time1": "32",
    "time2": "64",
    "placar1": "1",
    "placar2": "1"
  },
  {
    "id": 227,
    "pais": "Brasil",
    "ano": 2006,
    "serie": "A",
    "rodada": "23",
    "data": "2006-09-10",
    "horario": "18h10",
    "time1": "11",
    "time2": "30",
    "placar1": "0",
    "placar2": "2"
  },
  {
    "id": 228,
    "pais": "Brasil",
    "ano": 2006,
    "serie": "A",
    "rodada": "23",
    "data": "2006-09-10",
    "horario": "18h10",
    "time1": "40",
    "time2": "5",
    "placar1": "2",
    "placar2": "0"
  },
  {
    "id": 229,
    "pais": "Brasil",
    "ano": 2006,
    "serie": "A",
    "rodada": "24",
    "data": "2006-09-16",
    "horario": "16h00",
    "time1": "5",
    "time2": "62",
    "placar1": "2",
    "placar2": "1"
  },
  {
    "id": 230,
    "pais": "Brasil",
    "ano": 2006,
    "serie": "A",
    "rodada": "24",
    "data": "2006-09-16",
    "horario": "18h10",
    "time1": "71",
    "time2": "34",
    "placar1": "0",
    "placar2": "0"
  },
  {
    "id": 231,
    "pais": "Brasil",
    "ano": 2006,
    "serie": "A",
    "rodada": "24",
    "data": "2006-09-16",
    "horario": "18h10",
    "time1": "21",
    "time2": "54",
    "placar1": "1",
    "placar2": "0"
  },
  {
    "id": 232,
    "pais": "Brasil",
    "ano": 2006,
    "serie": "A",
    "rodada": "24",
    "data": "2006-09-17",
    "horario": "16h00",
    "time1": "25",
    "time2": "53",
    "placar1": "1",
    "placar2": "0"
  },
  {
    "id": 233,
    "pais": "Brasil",
    "ano": 2006,
    "serie": "A",
    "rodada": "24",
    "data": "2006-09-17",
    "horario": "16h00",
    "time1": "44",
    "time2": "66",
    "placar1": "1",
    "placar2": "0"
  },
  {
    "id": 234,
    "pais": "Brasil",
    "ano": 2006,
    "serie": "A",
    "rodada": "24",
    "data": "2006-09-17",
    "horario": "16h00",
    "time1": "36",
    "time2": "11",
    "placar1": "4",
    "placar2": "0"
  },
  {
    "id": 235,
    "pais": "Brasil",
    "ano": 2006,
    "serie": "A",
    "rodada": "24",
    "data": "2006-09-17",
    "horario": "16h00",
    "time1": "67",
    "time2": "40",
    "placar1": "2",
    "placar2": "0"
  },
  {
    "id": 236,
    "pais": "Brasil",
    "ano": 2006,
    "serie": "A",
    "rodada": "24",
    "data": "2006-09-17",
    "horario": "18h10",
    "time1": "57",
    "time2": "64",
    "placar1": "1",
    "placar2": "0"
  },
  {
    "id": 237,
    "pais": "Brasil",
    "ano": 2006,
    "serie": "A",
    "rodada": "24",
    "data": "2006-09-17",
    "horario": "18h10",
    "time1": "32",
    "time2": "30",
    "placar1": "3",
    "placar2": "4"
  },
  {
    "id": 238,
    "pais": "Brasil",
    "ano": 2006,
    "serie": "A",
    "rodada": "24",
    "data": "2006-09-17",
    "horario": "18h10",
    "time1": "31",
    "time2": "29",
    "placar1": "2",
    "placar2": "0"
  },
  {
    "id": 239,
    "pais": "Brasil",
    "ano": 2006,
    "serie": "A",
    "rodada": "25",
    "data": "2006-09-20",
    "horario": "16h00",
    "time1": "36",
    "time2": "57",
    "placar1": "4",
    "placar2": "0"
  },
  {
    "id": 240,
    "pais": "Brasil",
    "ano": 2006,
    "serie": "A",
    "rodada": "25",
    "data": "2006-09-20",
    "horario": "19h30",
    "time1": "29",
    "time2": "40",
    "placar1": "1",
    "placar2": "0"
  },
  {
    "id": 241,
    "pais": "Brasil",
    "ano": 2006,
    "serie": "A",
    "rodada": "25",
    "data": "2006-09-20",
    "horario": "19h30",
    "time1": "54",
    "time2": "32",
    "placar1": "2",
    "placar2": "0"
  },
  {
    "id": 242,
    "pais": "Brasil",
    "ano": 2006,
    "serie": "A",
    "rodada": "25",
    "data": "2006-09-20",
    "horario": "19h30",
    "time1": "11",
    "time2": "44",
    "placar1": "2",
    "placar2": "1"
  },
  {
    "id": 243,
    "pais": "Brasil",
    "ano": 2006,
    "serie": "A",
    "rodada": "25",
    "data": "2006-09-20",
    "horario": "20h30",
    "time1": "34",
    "time2": "5",
    "placar1": "2",
    "placar2": "2"
  },
  {
    "id": 244,
    "pais": "Brasil",
    "ano": 2006,
    "serie": "A",
    "rodada": "25",
    "data": "2006-09-20",
    "horario": "22h00",
    "time1": "64",
    "time2": "31",
    "placar1": "1",
    "placar2": "1"
  },
  {
    "id": 245,
    "pais": "Brasil",
    "ano": 2006,
    "serie": "A",
    "rodada": "25",
    "data": "2006-09-20",
    "horario": "22h00",
    "time1": "66",
    "time2": "67",
    "placar1": "0",
    "placar2": "1"
  },
  {
    "id": 246,
    "pais": "Brasil",
    "ano": 2006,
    "serie": "A",
    "rodada": "25",
    "data": "2006-09-20",
    "horario": "22h00",
    "time1": "21",
    "time2": "71",
    "placar1": "1",
    "placar2": "1"
  },
  {
    "id": 247,
    "pais": "Brasil",
    "ano": 2006,
    "serie": "A",
    "rodada": "25",
    "data": "2006-09-21",
    "horario": "20h30",
    "time1": "62",
    "time2": "53",
    "placar1": "3",
    "placar2": "2"
  },
  {
    "id": 248,
    "pais": "Brasil",
    "ano": 2006,
    "serie": "A",
    "rodada": "25",
    "data": "2006-09-21",
    "horario": "20h30",
    "time1": "30",
    "time2": "25",
    "placar1": "1",
    "placar2": "0"
  },
  {
    "id": 249,
    "pais": "Brasil",
    "ano": 2006,
    "serie": "A",
    "rodada": "26",
    "data": "2006-09-23",
    "horario": "16h00",
    "time1": "5",
    "time2": "66",
    "placar1": "3",
    "placar2": "1"
  },
  {
    "id": 250,
    "pais": "Brasil",
    "ano": 2006,
    "serie": "A",
    "rodada": "26",
    "data": "2006-09-23",
    "horario": "16h00",
    "time1": "31",
    "time2": "32",
    "placar1": "1",
    "placar2": "3"
  },
  {
    "id": 251,
    "pais": "Brasil",
    "ano": 2006,
    "serie": "A",
    "rodada": "26",
    "data": "2006-09-24",
    "horario": "16h00",
    "time1": "64",
    "time2": "30",
    "placar1": "3",
    "placar2": "0"
  },
  {
    "id": 252,
    "pais": "Brasil",
    "ano": 2006,
    "serie": "A",
    "rodada": "26",
    "data": "2006-09-24",
    "horario": "16h00",
    "time1": "62",
    "time2": "44",
    "placar1": "1",
    "placar2": "0"
  },
  {
    "id": 253,
    "pais": "Brasil",
    "ano": 2006,
    "serie": "A",
    "rodada": "26",
    "data": "2006-09-24",
    "horario": "16h00",
    "time1": "53",
    "time2": "67",
    "placar1": "3",
    "placar2": "1"
  },
  {
    "id": 254,
    "pais": "Brasil",
    "ano": 2006,
    "serie": "A",
    "rodada": "26",
    "data": "2006-09-24",
    "horario": "16h00",
    "time1": "40",
    "time2": "21",
    "placar1": "1",
    "placar2": "1"
  },
  {
    "id": 255,
    "pais": "Brasil",
    "ano": 2006,
    "serie": "A",
    "rodada": "26",
    "data": "2006-09-24",
    "horario": "16h00",
    "time1": "29",
    "time2": "54",
    "placar1": "0",
    "placar2": "1"
  },
  {
    "id": 256,
    "pais": "Brasil",
    "ano": 2006,
    "serie": "A",
    "rodada": "26",
    "data": "2006-09-24",
    "horario": "18h10",
    "time1": "34",
    "time2": "36",
    "placar1": "4",
    "placar2": "0"
  },
  {
    "id": 257,
    "pais": "Brasil",
    "ano": 2006,
    "serie": "A",
    "rodada": "26",
    "data": "2006-09-24",
    "horario": "18h10",
    "time1": "57",
    "time2": "25",
    "placar1": "0",
    "placar2": "1"
  },
  {
    "id": 258,
    "pais": "Brasil",
    "ano": 2006,
    "serie": "A",
    "rodada": "26",
    "data": "2006-09-24",
    "horario": "18h10",
    "time1": "71",
    "time2": "11",
    "placar1": "0",
    "placar2": "0"
  },
  {
    "id": 259,
    "pais": "Brasil",
    "ano": 2006,
    "serie": "A",
    "rodada": "17",
    "data": "2006-09-30",
    "horario": "16h00",
    "time1": "40",
    "time2": "54",
    "placar1": "3",
    "placar2": "2"
  },
  {
    "id": 260,
    "pais": "Brasil",
    "ano": 2006,
    "serie": "A",
    "rodada": "17",
    "data": "2006-09-30",
    "horario": "16h00",
    "time1": "5",
    "time2": "67",
    "placar1": "0",
    "placar2": "0"
  },
  {
    "id": 261,
    "pais": "Brasil",
    "ano": 2006,
    "serie": "A",
    "rodada": "27",
    "data": "2006-10-04",
    "horario": "19h30",
    "time1": "54",
    "time2": "57",
    "placar1": "2",
    "placar2": "1"
  },
  {
    "id": 262,
    "pais": "Brasil",
    "ano": 2006,
    "serie": "A",
    "rodada": "27",
    "data": "2006-10-04",
    "horario": "19h30",
    "time1": "32",
    "time2": "29",
    "placar1": "1",
    "placar2": "1"
  },
  {
    "id": 263,
    "pais": "Brasil",
    "ano": 2006,
    "serie": "A",
    "rodada": "27",
    "data": "2006-10-04",
    "horario": "19h30",
    "time1": "44",
    "time2": "5",
    "placar1": "3",
    "placar2": "2"
  },
  {
    "id": 264,
    "pais": "Brasil",
    "ano": 2006,
    "serie": "A",
    "rodada": "27",
    "data": "2006-10-04",
    "horario": "20h30",
    "time1": "30",
    "time2": "31",
    "placar1": "4",
    "placar2": "1"
  },
  {
    "id": 265,
    "pais": "Brasil",
    "ano": 2006,
    "serie": "A",
    "rodada": "27",
    "data": "2006-10-04",
    "horario": "22h00",
    "time1": "66",
    "time2": "34",
    "placar1": "1",
    "placar2": "2"
  },
  {
    "id": 266,
    "pais": "Brasil",
    "ano": 2006,
    "serie": "A",
    "rodada": "27",
    "data": "2006-10-04",
    "horario": "22h00",
    "time1": "36",
    "time2": "53",
    "placar1": "2",
    "placar2": "1"
  },
  {
    "id": 267,
    "pais": "Brasil",
    "ano": 2006,
    "serie": "A",
    "rodada": "27",
    "data": "2006-10-04",
    "horario": "22h00",
    "time1": "67",
    "time2": "71",
    "placar1": "5",
    "placar2": "1"
  },
  {
    "id": 268,
    "pais": "Brasil",
    "ano": 2006,
    "serie": "A",
    "rodada": "27",
    "data": "2006-10-05",
    "horario": "20h30",
    "time1": "11",
    "time2": "62",
    "placar1": "3",
    "placar2": "0"
  },
  {
    "id": 269,
    "pais": "Brasil",
    "ano": 2006,
    "serie": "A",
    "rodada": "27",
    "data": "2006-10-05",
    "horario": "20h30",
    "time1": "21",
    "time2": "64",
    "placar1": "0",
    "placar2": "3"
  },
  {
    "id": 270,
    "pais": "Brasil",
    "ano": 2006,
    "serie": "A",
    "rodada": "27",
    "data": "2006-10-05",
    "horario": "20h30",
    "time1": "25",
    "time2": "40",
    "placar1": "2",
    "placar2": "1"
  },
  {
    "id": 271,
    "pais": "Brasil",
    "ano": 2006,
    "serie": "A",
    "rodada": "28",
    "data": "2006-10-07",
    "horario": "16h00",
    "time1": "57",
    "time2": "44",
    "placar1": "3",
    "placar2": "1"
  },
  {
    "id": 272,
    "pais": "Brasil",
    "ano": 2006,
    "serie": "A",
    "rodada": "28",
    "data": "2006-10-07",
    "horario": "18h10",
    "time1": "31",
    "time2": "67",
    "placar1": "1",
    "placar2": "2"
  },
  {
    "id": 273,
    "pais": "Brasil",
    "ano": 2006,
    "serie": "A",
    "rodada": "28",
    "data": "2006-10-07",
    "horario": "18h10",
    "time1": "71",
    "time2": "32",
    "placar1": "2",
    "placar2": "0"
  },
  {
    "id": 274,
    "pais": "Brasil",
    "ano": 2006,
    "serie": "A",
    "rodada": "28",
    "data": "2006-10-08",
    "horario": "16h00",
    "time1": "53",
    "time2": "30",
    "placar1": "3",
    "placar2": "1"
  },
  {
    "id": 275,
    "pais": "Brasil",
    "ano": 2006,
    "serie": "A",
    "rodada": "28",
    "data": "2006-10-08",
    "horario": "16h00",
    "time1": "40",
    "time2": "66",
    "placar1": "1",
    "placar2": "0"
  },
  {
    "id": 276,
    "pais": "Brasil",
    "ano": 2006,
    "serie": "A",
    "rodada": "28",
    "data": "2006-10-08",
    "horario": "16h00",
    "time1": "62",
    "time2": "54",
    "placar1": "1",
    "placar2": "3"
  },
  {
    "id": 277,
    "pais": "Brasil",
    "ano": 2006,
    "serie": "A",
    "rodada": "28",
    "data": "2006-10-08",
    "horario": "16h00",
    "time1": "34",
    "time2": "21",
    "placar1": "3",
    "placar2": "1"
  },
  {
    "id": 278,
    "pais": "Brasil",
    "ano": 2006,
    "serie": "A",
    "rodada": "28",
    "data": "2006-10-08",
    "horario": "16h00",
    "time1": "5",
    "time2": "25",
    "placar1": "1",
    "placar2": "1"
  },
  {
    "id": 279,
    "pais": "Brasil",
    "ano": 2006,
    "serie": "A",
    "rodada": "28",
    "data": "2006-10-08",
    "horario": "18h10",
    "time1": "64",
    "time2": "36",
    "placar1": "1",
    "placar2": "0"
  },
  {
    "id": 280,
    "pais": "Brasil",
    "ano": 2006,
    "serie": "A",
    "rodada": "28",
    "data": "2006-10-08",
    "horario": "18h10",
    "time1": "29",
    "time2": "11",
    "placar1": "1",
    "placar2": "0"
  },
  {
    "id": 281,
    "pais": "Brasil",
    "ano": 2006,
    "serie": "A",
    "rodada": "29",
    "data": "2006-10-14",
    "horario": "16h00",
    "time1": "25",
    "time2": "32",
    "placar1": "0",
    "placar2": "0"
  },
  {
    "id": 282,
    "pais": "Brasil",
    "ano": 2006,
    "serie": "A",
    "rodada": "29",
    "data": "2006-10-14",
    "horario": "18h10",
    "time1": "66",
    "time2": "36",
    "placar1": "0",
    "placar2": "2"
  },
  {
    "id": 283,
    "pais": "Brasil",
    "ano": 2006,
    "serie": "A",
    "rodada": "29",
    "data": "2006-10-14",
    "horario": "18h10",
    "time1": "11",
    "time2": "64",
    "placar1": "4",
    "placar2": "3"
  },
  {
    "id": 284,
    "pais": "Brasil",
    "ano": 2006,
    "serie": "A",
    "rodada": "29",
    "data": "2006-10-14",
    "horario": "18h10",
    "time1": "67",
    "time2": "44",
    "placar1": "5",
    "placar2": "0"
  },
  {
    "id": 285,
    "pais": "Brasil",
    "ano": 2006,
    "serie": "A",
    "rodada": "29",
    "data": "2006-10-15",
    "horario": "16h00",
    "time1": "54",
    "time2": "34",
    "placar1": "1",
    "placar2": "0"
  },
  {
    "id": 286,
    "pais": "Brasil",
    "ano": 2006,
    "serie": "A",
    "rodada": "29",
    "data": "2006-10-15",
    "horario": "16h00",
    "time1": "29",
    "time2": "57",
    "placar1": "2",
    "placar2": "1"
  },
  {
    "id": 287,
    "pais": "Brasil",
    "ano": 2006,
    "serie": "A",
    "rodada": "29",
    "data": "2006-10-15",
    "horario": "16h00",
    "time1": "40",
    "time2": "31",
    "placar1": "2",
    "placar2": "0"
  },
  {
    "id": 288,
    "pais": "Brasil",
    "ano": 2006,
    "serie": "A",
    "rodada": "29",
    "data": "2006-10-15",
    "horario": "16h00",
    "time1": "30",
    "time2": "21",
    "placar1": "3",
    "placar2": "0"
  },
  {
    "id": 289,
    "pais": "Brasil",
    "ano": 2006,
    "serie": "A",
    "rodada": "29",
    "data": "2006-10-15",
    "horario": "18h10",
    "time1": "53",
    "time2": "5",
    "placar1": "2",
    "placar2": "2"
  },
  {
    "id": 290,
    "pais": "Brasil",
    "ano": 2006,
    "serie": "A",
    "rodada": "29",
    "data": "2006-10-15",
    "horario": "18h10",
    "time1": "62",
    "time2": "71",
    "placar1": "0",
    "placar2": "4"
  },
  {
    "id": 291,
    "pais": "Brasil",
    "ano": 2006,
    "serie": "A",
    "rodada": "30",
    "data": "2006-10-18",
    "horario": "22h00",
    "time1": "71",
    "time2": "53",
    "placar1": "3",
    "placar2": "0"
  },
  {
    "id": 292,
    "pais": "Brasil",
    "ano": 2006,
    "serie": "A",
    "rodada": "30",
    "data": "2006-10-21",
    "horario": "16h00",
    "time1": "34",
    "time2": "62",
    "placar1": "5",
    "placar2": "3"
  },
  {
    "id": 293,
    "pais": "Brasil",
    "ano": 2006,
    "serie": "A",
    "rodada": "30",
    "data": "2006-10-21",
    "horario": "18h10",
    "time1": "57",
    "time2": "40",
    "placar1": "0",
    "placar2": "2"
  },
  {
    "id": 294,
    "pais": "Brasil",
    "ano": 2006,
    "serie": "A",
    "rodada": "30",
    "data": "2006-10-21",
    "horario": "18h10",
    "time1": "64",
    "time2": "29",
    "placar1": "2",
    "placar2": "1"
  },
  {
    "id": 295,
    "pais": "Brasil",
    "ano": 2006,
    "serie": "A",
    "rodada": "30",
    "data": "2006-10-22",
    "horario": "16h00",
    "time1": "54",
    "time2": "30",
    "placar1": "0",
    "placar2": "2"
  },
  {
    "id": 296,
    "pais": "Brasil",
    "ano": 2006,
    "serie": "A",
    "rodada": "30",
    "data": "2006-10-22",
    "horario": "16h00",
    "time1": "32",
    "time2": "5",
    "placar1": "3",
    "placar2": "4"
  },
  {
    "id": 297,
    "pais": "Brasil",
    "ano": 2006,
    "serie": "A",
    "rodada": "30",
    "data": "2006-10-22",
    "horario": "16h00",
    "time1": "36",
    "time2": "67",
    "placar1": "1",
    "placar2": "1"
  },
  {
    "id": 298,
    "pais": "Brasil",
    "ano": 2006,
    "serie": "A",
    "rodada": "30",
    "data": "2006-10-22",
    "horario": "18h10",
    "time1": "11",
    "time2": "66",
    "placar1": "2",
    "placar2": "1"
  },
  {
    "id": 299,
    "pais": "Brasil",
    "ano": 2006,
    "serie": "A",
    "rodada": "30",
    "data": "2006-10-22",
    "horario": "18h10",
    "time1": "21",
    "time2": "25",
    "placar1": "1",
    "placar2": "0"
  },
  {
    "id": 300,
    "pais": "Brasil",
    "ano": 2006,
    "serie": "A",
    "rodada": "30",
    "data": "2006-10-22",
    "horario": "18h10",
    "time1": "44",
    "time2": "31",
    "placar1": "1",
    "placar2": "1"
  },
  {
    "id": 301,
    "pais": "Brasil",
    "ano": 2006,
    "serie": "A",
    "rodada": "31",
    "data": "2006-10-25",
    "horario": "22h00",
    "time1": "21",
    "time2": "53",
    "placar1": "1",
    "placar2": "0"
  },
  {
    "id": 302,
    "pais": "Brasil",
    "ano": 2006,
    "serie": "A",
    "rodada": "31",
    "data": "2006-10-26",
    "horario": "20h30",
    "time1": "62",
    "time2": "32",
    "placar1": "0",
    "placar2": "1"
  },
  {
    "id": 303,
    "pais": "Brasil",
    "ano": 2006,
    "serie": "A",
    "rodada": "31",
    "data": "2006-10-26",
    "horario": "20h30",
    "time1": "71",
    "time2": "30",
    "placar1": "3",
    "placar2": "1"
  },
  {
    "id": 304,
    "pais": "Brasil",
    "ano": 2006,
    "serie": "A",
    "rodada": "31",
    "data": "2006-10-26",
    "horario": "20h30",
    "time1": "40",
    "time2": "44",
    "placar1": "1",
    "placar2": "0"
  },
  {
    "id": 305,
    "pais": "Brasil",
    "ano": 2006,
    "serie": "A",
    "rodada": "31",
    "data": "2006-10-26",
    "horario": "20h30",
    "time1": "31",
    "time2": "36",
    "placar1": "1",
    "placar2": "2"
  },
  {
    "id": 306,
    "pais": "Brasil",
    "ano": 2006,
    "serie": "A",
    "rodada": "31",
    "data": "2006-10-28",
    "horario": "16h00",
    "time1": "5",
    "time2": "54",
    "placar1": "4",
    "placar2": "0"
  },
  {
    "id": 307,
    "pais": "Brasil",
    "ano": 2006,
    "serie": "A",
    "rodada": "31",
    "data": "2006-10-28",
    "horario": "16h00",
    "time1": "29",
    "time2": "67",
    "placar1": "0",
    "placar2": "2"
  },
  {
    "id": 308,
    "pais": "Brasil",
    "ano": 2006,
    "serie": "A",
    "rodada": "31",
    "data": "2006-10-28",
    "horario": "16h00",
    "time1": "57",
    "time2": "11",
    "placar1": "1",
    "placar2": "2"
  },
  {
    "id": 309,
    "pais": "Brasil",
    "ano": 2006,
    "serie": "A",
    "rodada": "31",
    "data": "2006-10-28",
    "horario": "18h10",
    "time1": "34",
    "time2": "25",
    "placar1": "2",
    "placar2": "3"
  },
  {
    "id": 310,
    "pais": "Brasil",
    "ano": 2006,
    "serie": "A",
    "rodada": "31",
    "data": "2006-10-28",
    "horario": "18h10",
    "time1": "64",
    "time2": "66",
    "placar1": "1",
    "placar2": "0"
  },
  {
    "id": 311,
    "pais": "Brasil",
    "ano": 2006,
    "serie": "A",
    "rodada": "32",
    "data": "2006-11-01",
    "horario": "19h30",
    "time1": "30",
    "time2": "62",
    "placar1": "1",
    "placar2": "1"
  },
  {
    "id": 312,
    "pais": "Brasil",
    "ano": 2006,
    "serie": "A",
    "rodada": "32",
    "data": "2006-11-01",
    "horario": "19h30",
    "time1": "53",
    "time2": "34",
    "placar1": "1",
    "placar2": "3"
  },
  {
    "id": 313,
    "pais": "Brasil",
    "ano": 2006,
    "serie": "A",
    "rodada": "32",
    "data": "2006-11-01",
    "horario": "19h30",
    "time1": "5",
    "time2": "71",
    "placar1": "6",
    "placar2": "4"
  },
  {
    "id": 314,
    "pais": "Brasil",
    "ano": 2006,
    "serie": "A",
    "rodada": "32",
    "data": "2006-11-01",
    "horario": "20h30",
    "time1": "36",
    "time2": "29",
    "placar1": "1",
    "placar2": "2"
  },
  {
    "id": 315,
    "pais": "Brasil",
    "ano": 2006,
    "serie": "A",
    "rodada": "32",
    "data": "2006-11-01",
    "horario": "21h45",
    "time1": "66",
    "time2": "31",
    "placar1": "1",
    "placar2": "1"
  },
  {
    "id": 316,
    "pais": "Brasil",
    "ano": 2006,
    "serie": "A",
    "rodada": "32",
    "data": "2006-11-01",
    "horario": "21h45",
    "time1": "32",
    "time2": "21",
    "placar1": "0",
    "placar2": "4"
  },
  {
    "id": 317,
    "pais": "Brasil",
    "ano": 2006,
    "serie": "A",
    "rodada": "32",
    "data": "2006-11-01",
    "horario": "21h45",
    "time1": "44",
    "time2": "64",
    "placar1": "3",
    "placar2": "2"
  },
  {
    "id": 318,
    "pais": "Brasil",
    "ano": 2006,
    "serie": "A",
    "rodada": "32",
    "data": "2006-11-02",
    "horario": "20h30",
    "time1": "67",
    "time2": "57",
    "placar1": "1",
    "placar2": "1"
  },
  {
    "id": 319,
    "pais": "Brasil",
    "ano": 2006,
    "serie": "A",
    "rodada": "32",
    "data": "2006-11-02",
    "horario": "20h30",
    "time1": "25",
    "time2": "54",
    "placar1": "2",
    "placar2": "2"
  },
  {
    "id": 320,
    "pais": "Brasil",
    "ano": 2006,
    "serie": "A",
    "rodada": "32",
    "data": "2006-11-02",
    "horario": "20h30",
    "time1": "11",
    "time2": "40",
    "placar1": "0",
    "placar2": "1"
  },
  {
    "id": 321,
    "pais": "Brasil",
    "ano": 2006,
    "serie": "A",
    "rodada": "33",
    "data": "2006-11-04",
    "horario": "18h10",
    "time1": "29",
    "time2": "44",
    "placar1": "1",
    "placar2": "0"
  },
  {
    "id": 322,
    "pais": "Brasil",
    "ano": 2006,
    "serie": "A",
    "rodada": "33",
    "data": "2006-11-04",
    "horario": "18h10",
    "time1": "30",
    "time2": "5",
    "placar1": "1",
    "placar2": "0"
  },
  {
    "id": 323,
    "pais": "Brasil",
    "ano": 2006,
    "serie": "A",
    "rodada": "33",
    "data": "2006-11-05",
    "horario": "16h00",
    "time1": "32",
    "time2": "34",
    "placar1": "0",
    "placar2": "3"
  },
  {
    "id": 324,
    "pais": "Brasil",
    "ano": 2006,
    "serie": "A",
    "rodada": "33",
    "data": "2006-11-05",
    "horario": "16h00",
    "time1": "64",
    "time2": "67",
    "placar1": "0",
    "placar2": "1"
  },
  {
    "id": 325,
    "pais": "Brasil",
    "ano": 2006,
    "serie": "A",
    "rodada": "33",
    "data": "2006-11-05",
    "horario": "16h00",
    "time1": "36",
    "time2": "40",
    "placar1": "0",
    "placar2": "1"
  },
  {
    "id": 326,
    "pais": "Brasil",
    "ano": 2006,
    "serie": "A",
    "rodada": "33",
    "data": "2006-11-05",
    "horario": "16h00",
    "time1": "25",
    "time2": "71",
    "placar1": "2",
    "placar2": "1"
  },
  {
    "id": 327,
    "pais": "Brasil",
    "ano": 2006,
    "serie": "A",
    "rodada": "33",
    "data": "2006-11-05",
    "horario": "16h00",
    "time1": "57",
    "time2": "66",
    "placar1": "1",
    "placar2": "2"
  },
  {
    "id": 328,
    "pais": "Brasil",
    "ano": 2006,
    "serie": "A",
    "rodada": "33",
    "data": "2006-11-05",
    "horario": "18h10",
    "time1": "54",
    "time2": "53",
    "placar1": "4",
    "placar2": "2"
  },
  {
    "id": 329,
    "pais": "Brasil",
    "ano": 2006,
    "serie": "A",
    "rodada": "33",
    "data": "2006-11-05",
    "horario": "18h10",
    "time1": "21",
    "time2": "62",
    "placar1": "1",
    "placar2": "0"
  },
  {
    "id": 330,
    "pais": "Brasil",
    "ano": 2006,
    "serie": "A",
    "rodada": "33",
    "data": "2006-11-05",
    "horario": "18h10",
    "time1": "11",
    "time2": "31",
    "placar1": "2",
    "placar2": "1"
  },
  {
    "id": 331,
    "pais": "Brasil",
    "ano": 2006,
    "serie": "A",
    "rodada": "34",
    "data": "2006-11-08",
    "horario": "19h30",
    "time1": "66",
    "time2": "29",
    "placar1": "3",
    "placar2": "1"
  },
  {
    "id": 332,
    "pais": "Brasil",
    "ano": 2006,
    "serie": "A",
    "rodada": "34",
    "data": "2006-11-08",
    "horario": "19h30",
    "time1": "71",
    "time2": "54",
    "placar1": "3",
    "placar2": "1"
  },
  {
    "id": 333,
    "pais": "Brasil",
    "ano": 2006,
    "serie": "A",
    "rodada": "34",
    "data": "2006-11-08",
    "horario": "19h30",
    "time1": "44",
    "time2": "36",
    "placar1": "1",
    "placar2": "2"
  },
  {
    "id": 334,
    "pais": "Brasil",
    "ano": 2006,
    "serie": "A",
    "rodada": "34",
    "data": "2006-11-08",
    "horario": "20h30",
    "time1": "53",
    "time2": "32",
    "placar1": "3",
    "placar2": "0"
  },
  {
    "id": 335,
    "pais": "Brasil",
    "ano": 2006,
    "serie": "A",
    "rodada": "34",
    "data": "2006-11-08",
    "horario": "21h45",
    "time1": "34",
    "time2": "30",
    "placar1": "0",
    "placar2": "1"
  },
  {
    "id": 336,
    "pais": "Brasil",
    "ano": 2006,
    "serie": "A",
    "rodada": "34",
    "data": "2006-11-08",
    "horario": "21h45",
    "time1": "40",
    "time2": "64",
    "placar1": "0",
    "placar2": "0"
  },
  {
    "id": 337,
    "pais": "Brasil",
    "ano": 2006,
    "serie": "A",
    "rodada": "34",
    "data": "2006-11-08",
    "horario": "21h45",
    "time1": "5",
    "time2": "21",
    "placar1": "1",
    "placar2": "2"
  },
  {
    "id": 338,
    "pais": "Brasil",
    "ano": 2006,
    "serie": "A",
    "rodada": "34",
    "data": "2006-11-09",
    "horario": "20h30",
    "time1": "67",
    "time2": "11",
    "placar1": "3",
    "placar2": "0"
  },
  {
    "id": 339,
    "pais": "Brasil",
    "ano": 2006,
    "serie": "A",
    "rodada": "34",
    "data": "2006-11-09",
    "horario": "20h30",
    "time1": "62",
    "time2": "25",
    "placar1": "4",
    "placar2": "1"
  },
  {
    "id": 340,
    "pais": "Brasil",
    "ano": 2006,
    "serie": "A",
    "rodada": "34",
    "data": "2006-11-09",
    "horario": "20h30",
    "time1": "31",
    "time2": "57",
    "placar1": "0",
    "placar2": "0"
  },
  {
    "id": 341,
    "pais": "Brasil",
    "ano": 2006,
    "serie": "A",
    "rodada": "35",
    "data": "2006-11-11",
    "horario": "18h10",
    "time1": "40",
    "time2": "32",
    "placar1": "3",
    "placar2": "0"
  },
  {
    "id": 342,
    "pais": "Brasil",
    "ano": 2006,
    "serie": "A",
    "rodada": "35",
    "data": "2006-11-11",
    "horario": "18h10",
    "time1": "64",
    "time2": "54",
    "placar1": "1",
    "placar2": "0"
  },
  {
    "id": 343,
    "pais": "Brasil",
    "ano": 2006,
    "serie": "A",
    "rodada": "35",
    "data": "2006-11-11",
    "horario": "18h10",
    "time1": "71",
    "time2": "44",
    "placar1": "1",
    "placar2": "1"
  },
  {
    "id": 344,
    "pais": "Brasil",
    "ano": 2006,
    "serie": "A",
    "rodada": "35",
    "data": "2006-11-12",
    "horario": "16h00",
    "time1": "57",
    "time2": "30",
    "placar1": "3",
    "placar2": "0"
  },
  {
    "id": 345,
    "pais": "Brasil",
    "ano": 2006,
    "serie": "A",
    "rodada": "35",
    "data": "2006-11-12",
    "horario": "16h00",
    "time1": "31",
    "time2": "25",
    "placar1": "1",
    "placar2": "0"
  },
  {
    "id": 346,
    "pais": "Brasil",
    "ano": 2006,
    "serie": "A",
    "rodada": "35",
    "data": "2006-11-12",
    "horario": "16h00",
    "time1": "29",
    "time2": "21",
    "placar1": "0",
    "placar2": "0"
  },
  {
    "id": 347,
    "pais": "Brasil",
    "ano": 2006,
    "serie": "A",
    "rodada": "35",
    "data": "2006-11-12",
    "horario": "16h00",
    "time1": "34",
    "time2": "67",
    "placar1": "0",
    "placar2": "2"
  },
  {
    "id": 348,
    "pais": "Brasil",
    "ano": 2006,
    "serie": "A",
    "rodada": "35",
    "data": "2006-11-12",
    "horario": "18h10",
    "time1": "53",
    "time2": "11",
    "placar1": "2",
    "placar2": "1"
  },
  {
    "id": 349,
    "pais": "Brasil",
    "ano": 2006,
    "serie": "A",
    "rodada": "35",
    "data": "2006-11-12",
    "horario": "18h10",
    "time1": "62",
    "time2": "66",
    "placar1": "0",
    "placar2": "3"
  },
  {
    "id": 350,
    "pais": "Brasil",
    "ano": 2006,
    "serie": "A",
    "rodada": "35",
    "data": "2006-11-12",
    "horario": "18h10",
    "time1": "5",
    "time2": "36",
    "placar1": "2",
    "placar2": "3"
  },
  {
    "id": 351,
    "pais": "Brasil",
    "ano": 2006,
    "serie": "A",
    "rodada": "36",
    "data": "2006-11-18",
    "horario": "18h10",
    "time1": "21",
    "time2": "31",
    "placar1": "1",
    "placar2": "1"
  },
  {
    "id": 352,
    "pais": "Brasil",
    "ano": 2006,
    "serie": "A",
    "rodada": "36",
    "data": "2006-11-18",
    "horario": "18h10",
    "time1": "30",
    "time2": "29",
    "placar1": "0",
    "placar2": "2"
  },
  {
    "id": 353,
    "pais": "Brasil",
    "ano": 2006,
    "serie": "A",
    "rodada": "36",
    "data": "2006-11-18",
    "horario": "18h10",
    "time1": "36",
    "time2": "62",
    "placar1": "3",
    "placar2": "1"
  },
  {
    "id": 354,
    "pais": "Brasil",
    "ano": 2006,
    "serie": "A",
    "rodada": "36",
    "data": "2006-11-19",
    "horario": "16h00",
    "time1": "44",
    "time2": "53",
    "placar1": "3",
    "placar2": "2"
  },
  {
    "id": 355,
    "pais": "Brasil",
    "ano": 2006,
    "serie": "A",
    "rodada": "36",
    "data": "2006-11-19",
    "horario": "16h00",
    "time1": "67",
    "time2": "5",
    "placar1": "1",
    "placar2": "1"
  },
  {
    "id": 356,
    "pais": "Brasil",
    "ano": 2006,
    "serie": "A",
    "rodada": "36",
    "data": "2006-11-19",
    "horario": "16h00",
    "time1": "66",
    "time2": "71",
    "placar1": "0",
    "placar2": "1"
  },
  {
    "id": 357,
    "pais": "Brasil",
    "ano": 2006,
    "serie": "A",
    "rodada": "36",
    "data": "2006-11-19",
    "horario": "16h00",
    "time1": "54",
    "time2": "40",
    "placar1": "1",
    "placar2": "0"
  },
  {
    "id": 358,
    "pais": "Brasil",
    "ano": 2006,
    "serie": "A",
    "rodada": "36",
    "data": "2006-11-19",
    "horario": "18h10",
    "time1": "32",
    "time2": "57",
    "placar1": "1",
    "placar2": "0"
  },
  {
    "id": 359,
    "pais": "Brasil",
    "ano": 2006,
    "serie": "A",
    "rodada": "36",
    "data": "2006-11-19",
    "horario": "18h10",
    "time1": "11",
    "time2": "34",
    "placar1": "2",
    "placar2": "2"
  },
  {
    "id": 360,
    "pais": "Brasil",
    "ano": 2006,
    "serie": "A",
    "rodada": "36",
    "data": "2006-11-19",
    "horario": "18h10",
    "time1": "25",
    "time2": "64",
    "placar1": "1",
    "placar2": "1"
  },
  {
    "id": 361,
    "pais": "Brasil",
    "ano": 2006,
    "serie": "A",
    "rodada": "37",
    "data": "2006-11-26",
    "horario": "16h00",
    "time1": "62",
    "time2": "31",
    "placar1": "1",
    "placar2": "2"
  },
  {
    "id": 362,
    "pais": "Brasil",
    "ano": 2006,
    "serie": "A",
    "rodada": "37",
    "data": "2006-11-26",
    "horario": "16h00",
    "time1": "66",
    "time2": "54",
    "placar1": "0",
    "placar2": "2"
  },
  {
    "id": 363,
    "pais": "Brasil",
    "ano": 2006,
    "serie": "A",
    "rodada": "37",
    "data": "2006-11-26",
    "horario": "16h00",
    "time1": "71",
    "time2": "64",
    "placar1": "1",
    "placar2": "1"
  },
  {
    "id": 364,
    "pais": "Brasil",
    "ano": 2006,
    "serie": "A",
    "rodada": "37",
    "data": "2006-11-26",
    "horario": "16h00",
    "time1": "53",
    "time2": "40",
    "placar1": "1",
    "placar2": "4"
  },
  {
    "id": 365,
    "pais": "Brasil",
    "ano": 2006,
    "serie": "A",
    "rodada": "37",
    "data": "2006-11-26",
    "horario": "16h00",
    "time1": "67",
    "time2": "25",
    "placar1": "2",
    "placar2": "0"
  },
  {
    "id": 366,
    "pais": "Brasil",
    "ano": 2006,
    "serie": "A",
    "rodada": "37",
    "data": "2006-11-26",
    "horario": "16h00",
    "time1": "44",
    "time2": "32",
    "placar1": "2",
    "placar2": "2"
  },
  {
    "id": 367,
    "pais": "Brasil",
    "ano": 2006,
    "serie": "A",
    "rodada": "37",
    "data": "2006-11-26",
    "horario": "16h00",
    "time1": "11",
    "time2": "21",
    "placar1": "0",
    "placar2": "0"
  },
  {
    "id": 368,
    "pais": "Brasil",
    "ano": 2006,
    "serie": "A",
    "rodada": "37",
    "data": "2006-11-26",
    "horario": "16h00",
    "time1": "5",
    "time2": "29",
    "placar1": "1",
    "placar2": "4"
  },
  {
    "id": 369,
    "pais": "Brasil",
    "ano": 2006,
    "serie": "A",
    "rodada": "37",
    "data": "2006-11-26",
    "horario": "16h00",
    "time1": "34",
    "time2": "57",
    "placar1": "3",
    "placar2": "0"
  },
  {
    "id": 370,
    "pais": "Brasil",
    "ano": 2006,
    "serie": "A",
    "rodada": "37",
    "data": "2006-11-26",
    "horario": "16h00",
    "time1": "36",
    "time2": "30",
    "placar1": "3",
    "placar2": "0"
  },
  {
    "id": 371,
    "pais": "Brasil",
    "ano": 2006,
    "serie": "A",
    "rodada": "38",
    "data": "2006-12-02",
    "horario": "18h10",
    "time1": "30",
    "time2": "66",
    "placar1": "4",
    "placar2": "1"
  },
  {
    "id": 372,
    "pais": "Brasil",
    "ano": 2006,
    "serie": "A",
    "rodada": "38",
    "data": "2006-12-02",
    "horario": "18h10",
    "time1": "40",
    "time2": "34",
    "placar1": "1",
    "placar2": "4"
  },
  {
    "id": 373,
    "pais": "Brasil",
    "ano": 2006,
    "serie": "A",
    "rodada": "38",
    "data": "2006-12-03",
    "horario": "16h00",
    "time1": "57",
    "time2": "5",
    "placar1": "1",
    "placar2": "1"
  },
  {
    "id": 374,
    "pais": "Brasil",
    "ano": 2006,
    "serie": "A",
    "rodada": "38",
    "data": "2006-12-03",
    "horario": "16h00",
    "time1": "54",
    "time2": "67",
    "placar1": "0",
    "placar2": "0"
  },
  {
    "id": 375,
    "pais": "Brasil",
    "ano": 2006,
    "serie": "A",
    "rodada": "38",
    "data": "2006-12-03",
    "horario": "16h00",
    "time1": "29",
    "time2": "71",
    "placar1": "0",
    "placar2": "0"
  },
  {
    "id": 376,
    "pais": "Brasil",
    "ano": 2006,
    "serie": "A",
    "rodada": "38",
    "data": "2006-12-03",
    "horario": "16h00",
    "time1": "21",
    "time2": "44",
    "placar1": "5",
    "placar2": "3"
  },
  {
    "id": 377,
    "pais": "Brasil",
    "ano": 2006,
    "serie": "A",
    "rodada": "38",
    "data": "2006-12-03",
    "horario": "16h00",
    "time1": "25",
    "time2": "11",
    "placar1": "3",
    "placar2": "1"
  },
  {
    "id": 378,
    "pais": "Brasil",
    "ano": 2006,
    "serie": "A",
    "rodada": "38",
    "data": "2006-12-03",
    "horario": "16h00",
    "time1": "31",
    "time2": "53",
    "placar1": "1",
    "placar2": "1"
  },
  {
    "id": 379,
    "pais": "Brasil",
    "ano": 2006,
    "serie": "A",
    "rodada": "38",
    "data": "2006-12-03",
    "horario": "18h10",
    "time1": "64",
    "time2": "62",
    "placar1": "3",
    "placar2": "1"
  },
  {
    "id": 380,
    "pais": "Brasil",
    "ano": 2006,
    "serie": "A",
    "rodada": "38",
    "data": "2006-12-03",
    "horario": "18h10",
    "time1": "32",
    "time2": "36",
    "placar1": "1",
    "placar2": "0"
  }
]
